{
"meta":{"test_sets":[],"test_metrics":[],"learn_metrics":[{"best_value":"Min","name":"Logloss"}],"launch_mode":"Train","parameters":"","iteration_count":1000,"learn_sets":["learn"],"name":"experiment"},
"iterations":[
{"learn":[0.5826974911],"iteration":0,"passed_time":0.1781768419,"remaining_time":177.9986651},
{"learn":[0.5009974931],"iteration":1,"passed_time":0.2082564697,"remaining_time":103.9199784},
{"learn":[0.4397091894],"iteration":2,"passed_time":0.2547458932,"remaining_time":84.66055184},
{"learn":[0.3981731695],"iteration":3,"passed_time":0.2814807046,"remaining_time":70.08869546},
{"learn":[0.363636131],"iteration":4,"passed_time":0.3131840283,"remaining_time":62.32362162},
{"learn":[0.3393245268],"iteration":5,"passed_time":0.3391988699,"remaining_time":56.19394611},
{"learn":[0.3198043258],"iteration":6,"passed_time":0.3708157456,"remaining_time":52.6028622},
{"learn":[0.3049464704],"iteration":7,"passed_time":0.400667284,"remaining_time":49.68274321},
{"learn":[0.292333105],"iteration":8,"passed_time":0.4314038196,"remaining_time":47.50235391},
{"learn":[0.2831950649],"iteration":9,"passed_time":0.4758757073,"remaining_time":47.11169502},
{"learn":[0.2752960192],"iteration":10,"passed_time":0.5081715356,"remaining_time":45.6892408},
{"learn":[0.2686630612],"iteration":11,"passed_time":0.5353352303,"remaining_time":44.07593396},
{"learn":[0.2638201523],"iteration":12,"passed_time":0.5780255849,"remaining_time":43.88548094},
{"learn":[0.2602023432],"iteration":13,"passed_time":0.6032794791,"remaining_time":42.48811188},
{"learn":[0.2575487755],"iteration":14,"passed_time":0.6263346352,"remaining_time":41.12930771},
{"learn":[0.2552162302],"iteration":15,"passed_time":0.6542995181,"remaining_time":40.23942036},
{"learn":[0.252869785],"iteration":16,"passed_time":0.696455769,"remaining_time":40.27153064},
{"learn":[0.2507169232],"iteration":17,"passed_time":0.7238003006,"remaining_time":39.48732751},
{"learn":[0.2493234852],"iteration":18,"passed_time":0.7555443472,"remaining_time":39.00994761},
{"learn":[0.2482306517],"iteration":19,"passed_time":0.7853461435,"remaining_time":38.48196103},
{"learn":[0.2472112712],"iteration":20,"passed_time":0.8226516671,"remaining_time":38.35123724},
{"learn":[0.2462134703],"iteration":21,"passed_time":0.8669445312,"remaining_time":38.53962507},
{"learn":[0.2451860168],"iteration":22,"passed_time":0.898555948,"remaining_time":38.16909397},
{"learn":[0.2438910562],"iteration":23,"passed_time":0.9304093877,"remaining_time":37.83664843},
{"learn":[0.2430673023],"iteration":24,"passed_time":0.9616931428,"remaining_time":37.50603257},
{"learn":[0.2425993469],"iteration":25,"passed_time":0.9920735325,"remaining_time":37.16460079},
{"learn":[0.2417843322],"iteration":26,"passed_time":1.021216948,"remaining_time":36.80163299},
{"learn":[0.2412615782],"iteration":27,"passed_time":1.055413107,"remaining_time":36.63791214},
{"learn":[0.2405948154],"iteration":28,"passed_time":1.085173595,"remaining_time":36.33460554},
{"learn":[0.2401459736],"iteration":29,"passed_time":1.134302558,"remaining_time":36.67578271},
{"learn":[0.2399267921],"iteration":30,"passed_time":1.17514323,"remaining_time":36.7327029},
{"learn":[0.2395982073],"iteration":31,"passed_time":1.20139494,"remaining_time":36.34219693},
{"learn":[0.2394431254],"iteration":32,"passed_time":1.232761092,"remaining_time":36.12363563},
{"learn":[0.2392411513],"iteration":33,"passed_time":1.265000042,"remaining_time":35.94088356},
{"learn":[0.2389649002],"iteration":34,"passed_time":1.298200118,"remaining_time":35.79323181},
{"learn":[0.2387208793],"iteration":35,"passed_time":1.324309955,"remaining_time":35.46207768},
{"learn":[0.2385566897],"iteration":36,"passed_time":1.348958701,"remaining_time":35.10938456},
{"learn":[0.2384469021],"iteration":37,"passed_time":1.381369454,"remaining_time":34.97045829},
{"learn":[0.2381366561],"iteration":38,"passed_time":1.418555445,"remaining_time":34.9546611},
{"learn":[0.238015763],"iteration":39,"passed_time":1.46200196,"remaining_time":35.08804705},
{"learn":[0.2379232171],"iteration":40,"passed_time":1.492381958,"remaining_time":34.907178},
{"learn":[0.2377465932],"iteration":41,"passed_time":1.535814282,"remaining_time":35.03119244},
{"learn":[0.2374833384],"iteration":42,"passed_time":1.576346977,"remaining_time":35.08288505},
{"learn":[0.2373965115],"iteration":43,"passed_time":1.603932158,"remaining_time":34.84907143},
{"learn":[0.2372508019],"iteration":44,"passed_time":1.636606326,"remaining_time":34.73242314},
{"learn":[0.2371553935],"iteration":45,"passed_time":1.68063867,"remaining_time":34.85498459},
{"learn":[0.2369587335],"iteration":46,"passed_time":1.712103363,"remaining_time":34.71562776},
{"learn":[0.2368857638],"iteration":47,"passed_time":1.73608827,"remaining_time":34.43241736},
{"learn":[0.2368163744],"iteration":48,"passed_time":1.777633854,"remaining_time":34.50060807},
{"learn":[0.2367366982],"iteration":49,"passed_time":1.8195978,"remaining_time":34.5723582},
{"learn":[0.2365721157],"iteration":50,"passed_time":1.864785936,"remaining_time":34.69964419},
{"learn":[0.2363854729],"iteration":51,"passed_time":1.907756541,"remaining_time":34.77986926},
{"learn":[0.236260312],"iteration":52,"passed_time":1.950800784,"remaining_time":34.85676118},
{"learn":[0.2361596592],"iteration":53,"passed_time":1.995839227,"remaining_time":34.96414645},
{"learn":[0.2359927704],"iteration":54,"passed_time":2.026695166,"remaining_time":34.82230784},
{"learn":[0.2358631221],"iteration":55,"passed_time":2.070999973,"remaining_time":34.9111424},
{"learn":[0.2358146416],"iteration":56,"passed_time":2.094085525,"remaining_time":34.64425702},
{"learn":[0.2356748744],"iteration":57,"passed_time":2.128007603,"remaining_time":34.56177865},
{"learn":[0.235574295],"iteration":58,"passed_time":2.159638395,"remaining_time":34.4444022},
{"learn":[0.2354734738],"iteration":59,"passed_time":2.190037573,"remaining_time":34.31058865},
{"learn":[0.2353716708],"iteration":60,"passed_time":2.236295582,"remaining_time":34.42428774},
{"learn":[0.2353173348],"iteration":61,"passed_time":2.263813299,"remaining_time":34.24930443},
{"learn":[0.2352690297],"iteration":62,"passed_time":2.308104545,"remaining_time":34.32847554},
{"learn":[0.2351958207],"iteration":63,"passed_time":2.33516759,"remaining_time":34.15182601},
{"learn":[0.2350969066],"iteration":64,"passed_time":2.363878758,"remaining_time":34.00348676},
{"learn":[0.2350529918],"iteration":65,"passed_time":2.391237733,"remaining_time":33.83963701},
{"learn":[0.2349885409],"iteration":66,"passed_time":2.427831494,"remaining_time":33.80845946},
{"learn":[0.2348856768],"iteration":67,"passed_time":2.477521187,"remaining_time":33.95661392},
{"learn":[0.2347887433],"iteration":68,"passed_time":2.515157218,"remaining_time":33.93639667},
{"learn":[0.2347371688],"iteration":69,"passed_time":2.54181113,"remaining_time":33.76977644},
{"learn":[0.2346790324],"iteration":70,"passed_time":2.57357362,"remaining_time":33.67394215},
{"learn":[0.2346349121],"iteration":71,"passed_time":2.604866078,"remaining_time":33.57382945},
{"learn":[0.2345999139],"iteration":72,"passed_time":2.632638847,"remaining_time":33.430907},
{"learn":[0.2345537606],"iteration":73,"passed_time":2.662287293,"remaining_time":33.31456802},
{"learn":[0.2345107063],"iteration":74,"passed_time":2.694364305,"remaining_time":33.2304931},
{"learn":[0.2344625057],"iteration":75,"passed_time":2.723558083,"remaining_time":33.11273249},
{"learn":[0.2344134939],"iteration":76,"passed_time":2.753228163,"remaining_time":33.00298175},
{"learn":[0.2343420449],"iteration":77,"passed_time":2.786107737,"remaining_time":32.93322222},
{"learn":[0.2342921016],"iteration":78,"passed_time":2.814439122,"remaining_time":32.81137255},
{"learn":[0.2342380697],"iteration":79,"passed_time":2.858936811,"remaining_time":32.87777332},
{"learn":[0.2342024359],"iteration":80,"passed_time":2.888490251,"remaining_time":32.77188322},
{"learn":[0.234147556],"iteration":81,"passed_time":2.919977809,"remaining_time":32.68950766},
{"learn":[0.2341001747],"iteration":82,"passed_time":2.949476816,"remaining_time":32.58638843},
{"learn":[0.2340559232],"iteration":83,"passed_time":2.977487014,"remaining_time":32.46878696},
{"learn":[0.2339779674],"iteration":84,"passed_time":3.020925351,"remaining_time":32.5193729},
{"learn":[0.2339044421],"iteration":85,"passed_time":3.069583251,"remaining_time":32.62324525},
{"learn":[0.2338643075],"iteration":86,"passed_time":3.11045058,"remaining_time":32.64185493},
{"learn":[0.2338145878],"iteration":87,"passed_time":3.141119962,"remaining_time":32.55342506},
{"learn":[0.2337805502],"iteration":88,"passed_time":3.169547635,"remaining_time":32.44334714},
{"learn":[0.2337466275],"iteration":89,"passed_time":3.216388769,"remaining_time":32.52126422},
{"learn":[0.2337080336],"iteration":90,"passed_time":3.245482924,"remaining_time":32.4191646},
{"learn":[0.2336683378],"iteration":91,"passed_time":3.272546114,"remaining_time":32.2986073},
{"learn":[0.2336200355],"iteration":92,"passed_time":3.303709675,"remaining_time":32.22005027},
{"learn":[0.2335724394],"iteration":93,"passed_time":3.332706957,"remaining_time":32.12162238},
{"learn":[0.233536983],"iteration":94,"passed_time":3.366601143,"remaining_time":32.07130562},
{"learn":[0.2334932581],"iteration":95,"passed_time":3.415235577,"remaining_time":32.16013502},
{"learn":[0.2334475611],"iteration":96,"passed_time":3.449821253,"remaining_time":32.1153463},
{"learn":[0.2333934453],"iteration":97,"passed_time":3.477413505,"remaining_time":32.00639777},
{"learn":[0.2333599239],"iteration":98,"passed_time":3.504788418,"remaining_time":31.89711479},
{"learn":[0.2333182871],"iteration":99,"passed_time":3.543753417,"remaining_time":31.89378076},
{"learn":[0.2332738125],"iteration":100,"passed_time":3.571809982,"remaining_time":31.79264528},
{"learn":[0.2332209379],"iteration":101,"passed_time":3.601655085,"remaining_time":31.70868888},
{"learn":[0.23317602],"iteration":102,"passed_time":3.631631919,"remaining_time":31.62693041},
{"learn":[0.2331362332],"iteration":103,"passed_time":3.663093087,"remaining_time":31.55895582},
{"learn":[0.2331202967],"iteration":104,"passed_time":3.69136128,"remaining_time":31.46446044},
{"learn":[0.233067468],"iteration":105,"passed_time":3.719799985,"remaining_time":31.37265271},
{"learn":[0.2330374075],"iteration":106,"passed_time":3.749612994,"remaining_time":31.2934991},
{"learn":[0.2329824918],"iteration":107,"passed_time":3.778443515,"remaining_time":31.20714459},
{"learn":[0.2329315818],"iteration":108,"passed_time":3.812037054,"remaining_time":31.16077995},
{"learn":[0.2328783685],"iteration":109,"passed_time":3.840886475,"remaining_time":31.0762633},
{"learn":[0.2328385576],"iteration":110,"passed_time":3.883490718,"remaining_time":31.10291214},
{"learn":[0.2327988932],"iteration":111,"passed_time":3.916788743,"remaining_time":31.05453932},
{"learn":[0.2327612775],"iteration":112,"passed_time":3.946938819,"remaining_time":30.9817233},
{"learn":[0.2327278073],"iteration":113,"passed_time":3.978794441,"remaining_time":30.92291118},
{"learn":[0.232689661],"iteration":114,"passed_time":4.018880556,"remaining_time":30.92790689},
{"learn":[0.2326579056],"iteration":115,"passed_time":4.06483218,"remaining_time":30.97682454},
{"learn":[0.2326154234],"iteration":116,"passed_time":4.092485975,"remaining_time":30.88602664},
{"learn":[0.2325494254],"iteration":117,"passed_time":4.122492131,"remaining_time":30.81388186},
{"learn":[0.2324980001],"iteration":118,"passed_time":4.152587983,"remaining_time":30.74310935},
{"learn":[0.2324630983],"iteration":119,"passed_time":4.180734706,"remaining_time":30.65872117},
{"learn":[0.2324097877],"iteration":120,"passed_time":4.20930001,"remaining_time":30.57830338},
{"learn":[0.2323726578],"iteration":121,"passed_time":4.241963602,"remaining_time":30.52822986},
{"learn":[0.2323291606],"iteration":122,"passed_time":4.272390107,"remaining_time":30.46248881},
{"learn":[0.2323021816],"iteration":123,"passed_time":4.302753926,"remaining_time":30.39687451},
{"learn":[0.2322625326],"iteration":124,"passed_time":4.332045084,"remaining_time":30.32431559},
{"learn":[0.2322147991],"iteration":125,"passed_time":4.395642304,"remaining_time":30.49040773},
{"learn":[0.2321823618],"iteration":126,"passed_time":4.44172905,"remaining_time":30.53251544},
{"learn":[0.2321465421],"iteration":127,"passed_time":4.480893966,"remaining_time":30.52609014},
{"learn":[0.2320840718],"iteration":128,"passed_time":4.509702163,"remaining_time":30.44922934},
{"learn":[0.2320554452],"iteration":129,"passed_time":4.541817865,"remaining_time":30.39524264},
{"learn":[0.2320076918],"iteration":130,"passed_time":4.569858715,"remaining_time":30.31455896},
{"learn":[0.2319695765],"iteration":131,"passed_time":4.596779466,"remaining_time":30.2273074},
{"learn":[0.2319191615],"iteration":132,"passed_time":4.629497501,"remaining_time":30.17875439},
{"learn":[0.2318938361],"iteration":133,"passed_time":4.655487986,"remaining_time":30.08695967},
{"learn":[0.2318446721],"iteration":134,"passed_time":4.688916171,"remaining_time":30.04379621},
{"learn":[0.2318108626],"iteration":135,"passed_time":4.717290613,"remaining_time":29.96866978},
{"learn":[0.2317751564],"iteration":136,"passed_time":4.744125302,"remaining_time":29.88452654},
{"learn":[0.2317420399],"iteration":137,"passed_time":4.779013798,"remaining_time":29.85152097},
{"learn":[0.2317045051],"iteration":138,"passed_time":4.806263774,"remaining_time":29.77117345},
{"learn":[0.2316604872],"iteration":139,"passed_time":4.837167531,"remaining_time":29.71402912},
{"learn":[0.2316214044],"iteration":140,"passed_time":4.869394484,"remaining_time":29.66531817},
{"learn":[0.23156684],"iteration":141,"passed_time":4.912078454,"remaining_time":29.68002333},
{"learn":[0.2315195374],"iteration":142,"passed_time":4.940506468,"remaining_time":29.60848981},
{"learn":[0.2314901169],"iteration":143,"passed_time":4.968231714,"remaining_time":29.53337741},
{"learn":[0.2314617984],"iteration":144,"passed_time":5.000224296,"remaining_time":29.4840812},
{"learn":[0.2314372435],"iteration":145,"passed_time":5.032986419,"remaining_time":29.4395233},
{"learn":[0.2313978463],"iteration":146,"passed_time":5.059353772,"remaining_time":29.35801883},
{"learn":[0.2313463798],"iteration":147,"passed_time":5.088837561,"remaining_time":29.29520001},
{"learn":[0.2313078065],"iteration":148,"passed_time":5.119762596,"remaining_time":29.24106019},
{"learn":[0.2312677087],"iteration":149,"passed_time":5.149910333,"remaining_time":29.18282522},
{"learn":[0.2312283729],"iteration":150,"passed_time":5.179379985,"remaining_time":29.12114972},
{"learn":[0.2311975152],"iteration":151,"passed_time":5.207625909,"remaining_time":29.05307086},
{"learn":[0.2311629755],"iteration":152,"passed_time":5.238057016,"remaining_time":28.99760976},
{"learn":[0.2311267596],"iteration":153,"passed_time":5.268765258,"remaining_time":28.94399616},
{"learn":[0.2310884051],"iteration":154,"passed_time":5.296913944,"remaining_time":28.8767244},
{"learn":[0.2310527162],"iteration":155,"passed_time":5.327954446,"remaining_time":28.82559969},
{"learn":[0.2310174329],"iteration":156,"passed_time":5.357401043,"remaining_time":28.76617248},
{"learn":[0.2309807012],"iteration":157,"passed_time":5.386256382,"remaining_time":28.70397388},
{"learn":[0.2309476363],"iteration":158,"passed_time":5.419674271,"remaining_time":28.66632743},
{"learn":[0.2309169383],"iteration":159,"passed_time":5.462127673,"remaining_time":28.67617028},
{"learn":[0.2308981344],"iteration":160,"passed_time":5.491089415,"remaining_time":28.61505602},
{"learn":[0.2308653769],"iteration":161,"passed_time":5.52255243,"remaining_time":28.56727739},
{"learn":[0.2308209383],"iteration":162,"passed_time":5.548263782,"remaining_time":28.49016433},
{"learn":[0.2307809568],"iteration":163,"passed_time":5.575608233,"remaining_time":28.42200294},
{"learn":[0.2307456907],"iteration":164,"passed_time":5.610784079,"remaining_time":28.39396792},
{"learn":[0.2307042981],"iteration":165,"passed_time":5.642009645,"remaining_time":28.34600027},
{"learn":[0.2306689119],"iteration":166,"passed_time":5.684502047,"remaining_time":28.35443236},
{"learn":[0.2306375967],"iteration":167,"passed_time":5.714276576,"remaining_time":28.29927447},
{"learn":[0.2306044606],"iteration":168,"passed_time":5.742894291,"remaining_time":28.23872873},
{"learn":[0.2305721162],"iteration":169,"passed_time":5.772938525,"remaining_time":28.18552339},
{"learn":[0.2305454422],"iteration":170,"passed_time":5.804126463,"remaining_time":28.13813355},
{"learn":[0.2305037327],"iteration":171,"passed_time":5.833035564,"remaining_time":28.0799619},
{"learn":[0.2304685721],"iteration":172,"passed_time":5.86336736,"remaining_time":28.02892952},
{"learn":[0.2304478201],"iteration":173,"passed_time":5.894222031,"remaining_time":27.98061723},
{"learn":[0.2304085392],"iteration":174,"passed_time":5.923466914,"remaining_time":27.92491545},
{"learn":[0.230368158],"iteration":175,"passed_time":5.955036327,"remaining_time":27.88039735},
{"learn":[0.2303253792],"iteration":176,"passed_time":6.000572848,"remaining_time":27.90096867},
{"learn":[0.2302943095],"iteration":177,"passed_time":6.028470248,"remaining_time":27.83934014},
{"learn":[0.2302626498],"iteration":178,"passed_time":6.056427335,"remaining_time":27.77836225},
{"learn":[0.2302358417],"iteration":179,"passed_time":6.090124763,"remaining_time":27.7439017},
{"learn":[0.2301959614],"iteration":180,"passed_time":6.120695449,"remaining_time":27.69530151},
{"learn":[0.2301587831],"iteration":181,"passed_time":6.164226945,"remaining_time":27.70515187},
{"learn":[0.2301260612],"iteration":182,"passed_time":6.194772447,"remaining_time":27.65644311},
{"learn":[0.2300788078],"iteration":183,"passed_time":6.224116882,"remaining_time":27.6026053},
{"learn":[0.2300405889],"iteration":184,"passed_time":6.253512896,"remaining_time":27.54925951},
{"learn":[0.2300097721],"iteration":185,"passed_time":6.281110661,"remaining_time":27.4883015},
{"learn":[0.229980771],"iteration":186,"passed_time":6.309866884,"remaining_time":27.43273677},
{"learn":[0.2299448514],"iteration":187,"passed_time":6.356054604,"remaining_time":27.45274648},
{"learn":[0.2299233705],"iteration":188,"passed_time":6.390413752,"remaining_time":27.42129922},
{"learn":[0.2299067577],"iteration":189,"passed_time":6.42743865,"remaining_time":27.40118582},
{"learn":[0.229874971],"iteration":190,"passed_time":6.460842689,"remaining_time":27.36555882},
{"learn":[0.2298508696],"iteration":191,"passed_time":6.49082056,"remaining_time":27.31553652},
{"learn":[0.2298182274],"iteration":192,"passed_time":6.521909787,"remaining_time":27.2703689},
{"learn":[0.2297881607],"iteration":193,"passed_time":6.565666668,"remaining_time":27.27797595},
{"learn":[0.2297604828],"iteration":194,"passed_time":6.607971121,"remaining_time":27.27906027},
{"learn":[0.2297262047],"iteration":195,"passed_time":6.637991468,"remaining_time":27.22931194},
{"learn":[0.2296922005],"iteration":196,"passed_time":6.669315044,"remaining_time":27.18507604},
{"learn":[0.2296533202],"iteration":197,"passed_time":6.698312362,"remaining_time":27.13154805},
{"learn":[0.2296277321],"iteration":198,"passed_time":6.728606438,"remaining_time":27.08348622},
{"learn":[0.2296029896],"iteration":199,"passed_time":6.76230601,"remaining_time":27.04922404},
{"learn":[0.2295687507],"iteration":200,"passed_time":6.802564424,"remaining_time":27.04103968},
{"learn":[0.2295425211],"iteration":201,"passed_time":6.832224858,"remaining_time":26.99067048},
{"learn":[0.2295111149],"iteration":202,"passed_time":6.862985436,"remaining_time":26.94482459},
{"learn":[0.2294786834],"iteration":203,"passed_time":6.909696815,"remaining_time":26.961366},
{"learn":[0.2294413929],"iteration":204,"passed_time":6.937565671,"remaining_time":26.90421809},
{"learn":[0.2294173731],"iteration":205,"passed_time":6.968610054,"remaining_time":26.85959409},
{"learn":[0.2293927867],"iteration":206,"passed_time":7.001590357,"remaining_time":26.82251765},
{"learn":[0.2293693607],"iteration":207,"passed_time":7.040272112,"remaining_time":26.80718996},
{"learn":[0.2293393091],"iteration":208,"passed_time":7.069632727,"remaining_time":26.75636118},
{"learn":[0.2293116081],"iteration":209,"passed_time":7.099981878,"remaining_time":26.70945564},
{"learn":[0.2292747514],"iteration":210,"passed_time":7.131222136,"remaining_time":26.66603917},
{"learn":[0.229238496],"iteration":211,"passed_time":7.17647924,"remaining_time":26.67483793},
{"learn":[0.2292123495],"iteration":212,"passed_time":7.20911561,"remaining_time":26.63649758},
{"learn":[0.2291715271],"iteration":213,"passed_time":7.237901974,"remaining_time":26.58406987},
{"learn":[0.2291414204],"iteration":214,"passed_time":7.268308929,"remaining_time":26.53777911},
{"learn":[0.2290960048],"iteration":215,"passed_time":7.298990109,"remaining_time":26.49263077},
{"learn":[0.2290580695],"iteration":216,"passed_time":7.338530892,"remaining_time":26.47958382},
{"learn":[0.2290342441],"iteration":217,"passed_time":7.366687855,"remaining_time":26.42545827},
{"learn":[0.2290170936],"iteration":218,"passed_time":7.398736659,"remaining_time":26.385449},
{"learn":[0.2289790312],"iteration":219,"passed_time":7.434641074,"remaining_time":26.35918199},
{"learn":[0.2289456238],"iteration":220,"passed_time":7.474289302,"remaining_time":26.34602428},
{"learn":[0.228912714],"iteration":221,"passed_time":7.516053922,"remaining_time":26.34004482},
{"learn":[0.22888416],"iteration":222,"passed_time":7.561981368,"remaining_time":26.34824898},
{"learn":[0.2288526862],"iteration":223,"passed_time":7.595363222,"remaining_time":26.31250831},
{"learn":[0.228826794],"iteration":224,"passed_time":7.629079945,"remaining_time":26.27794203},
{"learn":[0.2288034249],"iteration":225,"passed_time":7.668553695,"remaining_time":26.26309982},
{"learn":[0.2287760778],"iteration":226,"passed_time":7.704498371,"remaining_time":26.23602309},
{"learn":[0.2287466739],"iteration":227,"passed_time":7.754627043,"remaining_time":26.25689507},
{"learn":[0.2287199126],"iteration":228,"passed_time":7.79652066,"remaining_time":26.24942109},
{"learn":[0.228691188],"iteration":229,"passed_time":7.826362103,"remaining_time":26.20129921},
{"learn":[0.2286671093],"iteration":230,"passed_time":7.865335065,"remaining_time":26.18373448},
{"learn":[0.2286397159],"iteration":231,"passed_time":7.899504687,"remaining_time":26.15008448},
{"learn":[0.2286135777],"iteration":232,"passed_time":7.935677769,"remaining_time":26.1230251},
{"learn":[0.2285924439],"iteration":233,"passed_time":7.969259425,"remaining_time":26.08740478},
{"learn":[0.228569155],"iteration":234,"passed_time":8.006665192,"remaining_time":26.06425052},
{"learn":[0.2285503876],"iteration":235,"passed_time":8.05193558,"remaining_time":26.06643552},
{"learn":[0.2285176555],"iteration":236,"passed_time":8.080808862,"remaining_time":26.01543106},
{"learn":[0.2284907334],"iteration":237,"passed_time":8.113676427,"remaining_time":25.977401},
{"learn":[0.2284674772],"iteration":238,"passed_time":8.146840527,"remaining_time":25.94035833},
{"learn":[0.2284370563],"iteration":239,"passed_time":8.186750296,"remaining_time":25.92470927},
{"learn":[0.2284081743],"iteration":240,"passed_time":8.231751486,"remaining_time":25.92489368},
{"learn":[0.2283762273],"iteration":241,"passed_time":8.261083887,"remaining_time":25.87562639},
{"learn":[0.2283440494],"iteration":242,"passed_time":8.285235561,"remaining_time":25.81038403},
{"learn":[0.2283155917],"iteration":243,"passed_time":8.316328348,"remaining_time":25.76698455},
{"learn":[0.2282793647],"iteration":244,"passed_time":8.348399176,"remaining_time":25.7266995},
{"learn":[0.2282576852],"iteration":245,"passed_time":8.37886134,"remaining_time":25.68155061},
{"learn":[0.2282301473],"iteration":246,"passed_time":8.411276501,"remaining_time":25.64247452},
{"learn":[0.2282053876],"iteration":247,"passed_time":8.445032589,"remaining_time":25.60751817},
{"learn":[0.2281841357],"iteration":248,"passed_time":8.49993469,"remaining_time":25.6363492},
{"learn":[0.2281579864],"iteration":249,"passed_time":8.532248926,"remaining_time":25.59674678},
{"learn":[0.2281254563],"iteration":250,"passed_time":8.57452124,"remaining_time":25.58691796},
{"learn":[0.2281027597],"iteration":251,"passed_time":8.605394795,"remaining_time":25.54299725},
{"learn":[0.2280842005],"iteration":252,"passed_time":8.647460512,"remaining_time":25.53222531},
{"learn":[0.2280507289],"iteration":253,"passed_time":8.677725183,"remaining_time":25.48654719},
{"learn":[0.2280269105],"iteration":254,"passed_time":8.703654724,"remaining_time":25.42832459},
{"learn":[0.2280089735],"iteration":255,"passed_time":8.731598345,"remaining_time":25.37620769},
{"learn":[0.22797872],"iteration":256,"passed_time":8.76636929,"remaining_time":25.34401705},
{"learn":[0.2279577165],"iteration":257,"passed_time":8.797732267,"remaining_time":25.3020052},
{"learn":[0.2279447601],"iteration":258,"passed_time":8.83053337,"remaining_time":25.26419007},
{"learn":[0.2279170957],"iteration":259,"passed_time":8.859775493,"remaining_time":25.21628409},
{"learn":[0.2278905504],"iteration":260,"passed_time":8.88703251,"remaining_time":25.16290048},
{"learn":[0.227871563],"iteration":261,"passed_time":8.91630157,"remaining_time":25.11538381},
{"learn":[0.2278461672],"iteration":262,"passed_time":8.960136685,"remaining_time":25.1088241},
{"learn":[0.2278225396],"iteration":263,"passed_time":8.988085314,"remaining_time":25.05769239},
{"learn":[0.2277902147],"iteration":264,"passed_time":9.022025624,"remaining_time":25.02335409},
{"learn":[0.2277676678],"iteration":265,"passed_time":9.05238361,"remaining_time":24.97913372},
{"learn":[0.2277383707],"iteration":266,"passed_time":9.083425593,"remaining_time":24.93689498},
{"learn":[0.2277125917],"iteration":267,"passed_time":9.127671315,"remaining_time":24.93080374},
{"learn":[0.2276841008],"iteration":268,"passed_time":9.167248383,"remaining_time":24.91174189},
{"learn":[0.2276659963],"iteration":269,"passed_time":9.194711056,"remaining_time":24.85977434},
{"learn":[0.22763844],"iteration":270,"passed_time":9.226700073,"remaining_time":24.82016367},
{"learn":[0.227616549],"iteration":271,"passed_time":9.258418776,"remaining_time":24.77988555},
{"learn":[0.2275874338],"iteration":272,"passed_time":9.287647158,"remaining_time":24.7330384},
{"learn":[0.2275583775],"iteration":273,"passed_time":9.331580805,"remaining_time":24.72528345},
{"learn":[0.2275344983],"iteration":274,"passed_time":9.377157499,"remaining_time":24.72159704},
{"learn":[0.2275130489],"iteration":275,"passed_time":9.426777034,"remaining_time":24.72821222},
{"learn":[0.2274906306],"iteration":276,"passed_time":9.467753275,"remaining_time":24.71186144},
{"learn":[0.2274749872],"iteration":277,"passed_time":9.499379114,"remaining_time":24.67104935},
{"learn":[0.2274489853],"iteration":278,"passed_time":9.531190544,"remaining_time":24.63078273},
{"learn":[0.2274292218],"iteration":279,"passed_time":9.56114872,"remaining_time":24.585811},
{"learn":[0.2274069505],"iteration":280,"passed_time":9.592030558,"remaining_time":24.54330951},
{"learn":[0.2273750922],"iteration":281,"passed_time":9.622899397,"remaining_time":24.50085733},
{"learn":[0.2273420521],"iteration":282,"passed_time":9.651363066,"remaining_time":24.45239335},
{"learn":[0.2273122963],"iteration":283,"passed_time":9.687853159,"remaining_time":24.42430585},
{"learn":[0.2272877225],"iteration":284,"passed_time":9.719263839,"remaining_time":24.3834163},
{"learn":[0.2272577691],"iteration":285,"passed_time":9.764788883,"remaining_time":24.37782959},
{"learn":[0.2272297733],"iteration":286,"passed_time":9.809205406,"remaining_time":24.36921064},
{"learn":[0.2272113274],"iteration":287,"passed_time":9.839481665,"remaining_time":24.32538523},
{"learn":[0.2271855572],"iteration":288,"passed_time":9.884931048,"remaining_time":24.31898261},
{"learn":[0.2271611124],"iteration":289,"passed_time":9.915951729,"remaining_time":24.27698527},
{"learn":[0.227139438],"iteration":290,"passed_time":9.945642681,"remaining_time":24.23182358},
{"learn":[0.227118633],"iteration":291,"passed_time":9.990759534,"remaining_time":24.22417038},
{"learn":[0.2271008115],"iteration":292,"passed_time":10.03281497,"remaining_time":24.20887436},
{"learn":[0.2270811241],"iteration":293,"passed_time":10.09282545,"remaining_time":24.23651281},
{"learn":[0.2270586253],"iteration":294,"passed_time":10.12429122,"remaining_time":24.19534004},
{"learn":[0.2270340309],"iteration":295,"passed_time":10.17056788,"remaining_time":24.18945875},
{"learn":[0.2270144477],"iteration":296,"passed_time":10.20848837,"remaining_time":24.16352635},
{"learn":[0.2269926411],"iteration":297,"passed_time":10.23763454,"remaining_time":24.11684377},
{"learn":[0.2269775118],"iteration":298,"passed_time":10.26283435,"remaining_time":24.06102635},
{"learn":[0.2269577748],"iteration":299,"passed_time":10.29758599,"remaining_time":24.02770065},
{"learn":[0.2269286191],"iteration":300,"passed_time":10.32527617,"remaining_time":23.97796691},
{"learn":[0.2268986213],"iteration":301,"passed_time":10.35957754,"remaining_time":23.94365935},
{"learn":[0.2268750506],"iteration":302,"passed_time":10.41193857,"remaining_time":23.95089499},
{"learn":[0.2268597883],"iteration":303,"passed_time":10.45292998,"remaining_time":23.93170811},
{"learn":[0.2268359405],"iteration":304,"passed_time":10.4998715,"remaining_time":23.92593669},
{"learn":[0.2268005972],"iteration":305,"passed_time":10.54026786,"remaining_time":23.90505195},
{"learn":[0.2267693366],"iteration":306,"passed_time":10.56582811,"remaining_time":23.85055009},
{"learn":[0.226745142],"iteration":307,"passed_time":10.59986871,"remaining_time":23.81528944},
{"learn":[0.2267206817],"iteration":308,"passed_time":10.65886196,"remaining_time":23.83583694},
{"learn":[0.2266988959],"iteration":309,"passed_time":10.68964154,"remaining_time":23.7930731},
{"learn":[0.2266732921],"iteration":310,"passed_time":10.73008997,"remaining_time":23.77180703},
{"learn":[0.2266511689],"iteration":311,"passed_time":10.76207848,"remaining_time":23.73176281},
{"learn":[0.2266349635],"iteration":312,"passed_time":10.80776988,"remaining_time":23.72184635},
{"learn":[0.2266024365],"iteration":313,"passed_time":10.85269078,"remaining_time":23.7100187},
{"learn":[0.2265774555],"iteration":314,"passed_time":10.8971609,"remaining_time":23.69700068},
{"learn":[0.2265552666],"iteration":315,"passed_time":10.9423265,"remaining_time":23.68528901},
{"learn":[0.2265279796],"iteration":316,"passed_time":10.98885001,"remaining_time":23.67629198},
{"learn":[0.2265105707],"iteration":317,"passed_time":11.03258834,"remaining_time":23.66108569},
{"learn":[0.2264858848],"iteration":318,"passed_time":11.0676019,"remaining_time":23.62707491},
{"learn":[0.2264715348],"iteration":319,"passed_time":11.10566378,"remaining_time":23.59953552},
{"learn":[0.2264496488],"iteration":320,"passed_time":11.14966019,"remaining_time":23.58448371},
{"learn":[0.2264284336],"iteration":321,"passed_time":11.19429991,"remaining_time":23.57060663},
{"learn":[0.2264054898],"iteration":322,"passed_time":11.24298639,"remaining_time":23.56502102},
{"learn":[0.2263792514],"iteration":323,"passed_time":11.28482573,"remaining_time":23.54488332},
{"learn":[0.2263603013],"iteration":324,"passed_time":11.32655228,"remaining_time":23.52437781},
{"learn":[0.2263370864],"iteration":325,"passed_time":11.35520346,"remaining_time":23.47670899},
{"learn":[0.2263113352],"iteration":326,"passed_time":11.38620028,"remaining_time":23.43398407},
{"learn":[0.226283889],"iteration":327,"passed_time":11.41984286,"remaining_time":23.39675122},
{"learn":[0.226269588],"iteration":328,"passed_time":11.45870092,"remaining_time":23.37017726},
{"learn":[0.2262487169],"iteration":329,"passed_time":11.48503605,"remaining_time":23.3181035},
{"learn":[0.2262320993],"iteration":330,"passed_time":11.51305016,"remaining_time":23.26957873},
{"learn":[0.2262154504],"iteration":331,"passed_time":11.55061356,"remaining_time":23.24039114},
{"learn":[0.2261964615],"iteration":332,"passed_time":11.58004611,"remaining_time":23.19486713},
{"learn":[0.2261758925],"iteration":333,"passed_time":11.61095961,"remaining_time":23.15239252},
{"learn":[0.2261646893],"iteration":334,"passed_time":11.63899608,"remaining_time":23.1042758},
{"learn":[0.2261389635],"iteration":335,"passed_time":11.67144,"remaining_time":23.06498858},
{"learn":[0.2261175811],"iteration":336,"passed_time":11.71491059,"remaining_time":23.04743537},
{"learn":[0.2261038884],"iteration":337,"passed_time":11.74189706,"remaining_time":22.99744335},
{"learn":[0.2260745285],"iteration":338,"passed_time":11.7712379,"remaining_time":22.95217774},
{"learn":[0.2260487859],"iteration":339,"passed_time":11.8183292,"remaining_time":22.94146256},
{"learn":[0.2260341437],"iteration":340,"passed_time":11.848051,"remaining_time":22.89696659},
{"learn":[0.2260141531],"iteration":341,"passed_time":11.87900088,"remaining_time":22.85491982},
{"learn":[0.2259919126],"iteration":342,"passed_time":11.90689945,"remaining_time":22.80709312},
{"learn":[0.2259672732],"iteration":343,"passed_time":11.9375322,"remaining_time":22.76459629},
{"learn":[0.2259431176],"iteration":344,"passed_time":11.96788958,"remaining_time":22.72164544},
{"learn":[0.22591717],"iteration":345,"passed_time":12.01189747,"remaining_time":22.7045692},
{"learn":[0.2258957135],"iteration":346,"passed_time":12.0556382,"remaining_time":22.68683499},
{"learn":[0.2258743273],"iteration":347,"passed_time":12.08591949,"remaining_time":22.64373422},
{"learn":[0.2258568322],"iteration":348,"passed_time":12.12985047,"remaining_time":22.62616806},
{"learn":[0.2258421572],"iteration":349,"passed_time":12.16069801,"remaining_time":22.58415345},
{"learn":[0.2258120879],"iteration":350,"passed_time":12.18876489,"remaining_time":22.537061},
{"learn":[0.2257955564],"iteration":351,"passed_time":12.21766778,"remaining_time":22.49161568},
{"learn":[0.2257767386],"iteration":352,"passed_time":12.26465741,"remaining_time":22.47941457},
{"learn":[0.2257520704],"iteration":353,"passed_time":12.3113138,"remaining_time":22.4664088},
{"learn":[0.2257208747],"iteration":354,"passed_time":12.35440865,"remaining_time":22.44674249},
{"learn":[0.2256944796],"iteration":355,"passed_time":12.3867832,"remaining_time":22.40755164},
{"learn":[0.2256699626],"iteration":356,"passed_time":12.41629493,"remaining_time":22.36324269},
{"learn":[0.2256509804],"iteration":357,"passed_time":12.44277875,"remaining_time":22.31358648},
{"learn":[0.2256277993],"iteration":358,"passed_time":12.47168393,"remaining_time":22.26838272},
{"learn":[0.225615818],"iteration":359,"passed_time":12.49918107,"remaining_time":22.22076635},
{"learn":[0.2255907517],"iteration":360,"passed_time":12.52690938,"remaining_time":22.17367063},
{"learn":[0.2255757647],"iteration":361,"passed_time":12.5594555,"remaining_time":22.13517295},
{"learn":[0.2255523597],"iteration":362,"passed_time":12.59156015,"remaining_time":22.09593338},
{"learn":[0.2255333832],"iteration":363,"passed_time":12.62130301,"remaining_time":22.05260636},
{"learn":[0.225505027],"iteration":364,"passed_time":12.6490653,"remaining_time":22.00590813},
{"learn":[0.2254859318],"iteration":365,"passed_time":12.68033463,"remaining_time":21.9653884},
{"learn":[0.2254625668],"iteration":366,"passed_time":12.70700661,"remaining_time":21.9169896},
{"learn":[0.2254385608],"iteration":367,"passed_time":12.73347075,"remaining_time":21.86835194},
{"learn":[0.2254285411],"iteration":368,"passed_time":12.76812764,"remaining_time":21.83384428},
{"learn":[0.2254048581],"iteration":369,"passed_time":12.79576613,"remaining_time":21.78738557},
{"learn":[0.2253831315],"iteration":370,"passed_time":12.82680875,"remaining_time":21.74679973},
{"learn":[0.2253626354],"iteration":371,"passed_time":12.85365621,"remaining_time":21.69918307},
{"learn":[0.2253442575],"iteration":372,"passed_time":12.88280809,"remaining_time":21.6555514},
{"learn":[0.2253247138],"iteration":373,"passed_time":12.91864439,"remaining_time":21.62318553},
{"learn":[0.2252954921],"iteration":374,"passed_time":12.94796065,"remaining_time":21.57993441},
{"learn":[0.2252703738],"iteration":375,"passed_time":12.97891487,"remaining_time":21.53947575},
{"learn":[0.2252440757],"iteration":376,"passed_time":13.02148008,"remaining_time":21.51825488},
{"learn":[0.2252232905],"iteration":377,"passed_time":13.04972626,"remaining_time":21.47335909},
{"learn":[0.2252063229],"iteration":378,"passed_time":13.07589742,"remaining_time":21.42515119},
{"learn":[0.2251889188],"iteration":379,"passed_time":13.10864805,"remaining_time":21.38779419},
{"learn":[0.2251707664],"iteration":380,"passed_time":13.13935882,"remaining_time":21.34714726},
{"learn":[0.2251498902],"iteration":381,"passed_time":13.17332073,"remaining_time":21.31181207},
{"learn":[0.2251234522],"iteration":382,"passed_time":13.20106875,"remaining_time":21.26647368},
{"learn":[0.2250971893],"iteration":383,"passed_time":13.22270173,"remaining_time":21.21141736},
{"learn":[0.2250818038],"iteration":384,"passed_time":13.24895386,"remaining_time":21.1639133},
{"learn":[0.2250605151],"iteration":385,"passed_time":13.3046166,"remaining_time":21.16330206},
{"learn":[0.2250371092],"iteration":386,"passed_time":13.33673134,"remaining_time":21.12510675},
{"learn":[0.2250088341],"iteration":387,"passed_time":13.3971931,"remaining_time":21.1316551},
{"learn":[0.2249945287],"iteration":388,"passed_time":13.42423823,"remaining_time":21.08537162},
{"learn":[0.2249693079],"iteration":389,"passed_time":13.45090876,"remaining_time":21.03860088},
{"learn":[0.224950611],"iteration":390,"passed_time":13.48669295,"remaining_time":21.00612789},
{"learn":[0.2249217316],"iteration":391,"passed_time":13.52688873,"remaining_time":20.98048049},
{"learn":[0.2248984455],"iteration":392,"passed_time":13.55735437,"remaining_time":20.93973055},
{"learn":[0.224878347],"iteration":393,"passed_time":13.58364886,"remaining_time":20.89261729},
{"learn":[0.2248565673],"iteration":394,"passed_time":13.61832109,"remaining_time":20.85844116},
{"learn":[0.2248453726],"iteration":395,"passed_time":13.64691111,"remaining_time":20.81498563},
{"learn":[0.2248250223],"iteration":396,"passed_time":13.67301071,"remaining_time":20.76782232},
{"learn":[0.2248090877],"iteration":397,"passed_time":13.70680442,"remaining_time":20.73240267},
{"learn":[0.2247891472],"iteration":398,"passed_time":13.73422578,"remaining_time":20.68739271},
{"learn":[0.2247680343],"iteration":399,"passed_time":13.7653944,"remaining_time":20.6480916},
{"learn":[0.2247503109],"iteration":400,"passed_time":13.7961238,"remaining_time":20.60817496},
{"learn":[0.2247326304],"iteration":401,"passed_time":13.8288729,"remaining_time":20.57130845},
{"learn":[0.2247111583],"iteration":402,"passed_time":13.87056086,"remaining_time":20.5477043},
{"learn":[0.2246930338],"iteration":403,"passed_time":13.9035248,"remaining_time":20.51114055},
{"learn":[0.2246672622],"iteration":404,"passed_time":13.945843,"remaining_time":20.48833724},
{"learn":[0.2246424119],"iteration":405,"passed_time":13.97537134,"remaining_time":20.44672556},
{"learn":[0.2246275415],"iteration":406,"passed_time":14.00731319,"remaining_time":20.40868973},
{"learn":[0.2246037523],"iteration":407,"passed_time":14.03684067,"remaining_time":20.36718058},
{"learn":[0.2245773849],"iteration":408,"passed_time":14.06959493,"remaining_time":20.33039267},
{"learn":[0.2245585163],"iteration":409,"passed_time":14.10142847,"remaining_time":20.29229951},
{"learn":[0.2245416886],"iteration":410,"passed_time":14.14389626,"remaining_time":20.26947664},
{"learn":[0.224526159],"iteration":411,"passed_time":14.17024076,"remaining_time":20.22354749},
{"learn":[0.2244986396],"iteration":412,"passed_time":14.19829375,"remaining_time":20.18014147},
{"learn":[0.2244785492],"iteration":413,"passed_time":14.22612896,"remaining_time":20.13650138},
{"learn":[0.2244592889],"iteration":414,"passed_time":14.26240266,"remaining_time":20.10483267},
{"learn":[0.2244368256],"iteration":415,"passed_time":14.29047221,"remaining_time":20.06162446},
{"learn":[0.2244153129],"iteration":416,"passed_time":14.33275217,"remaining_time":20.03835615},
{"learn":[0.2243876092],"iteration":417,"passed_time":14.36273967,"remaining_time":19.99788155},
{"learn":[0.2243539218],"iteration":418,"passed_time":14.39683734,"remaining_time":19.96315631},
{"learn":[0.2243306541],"iteration":419,"passed_time":14.42398986,"remaining_time":19.91884313},
{"learn":[0.2243083882],"iteration":420,"passed_time":14.46625597,"remaining_time":19.89539717},
{"learn":[0.2242866598],"iteration":421,"passed_time":14.49622733,"remaining_time":19.85502227},
{"learn":[0.2242508385],"iteration":422,"passed_time":14.52769116,"remaining_time":19.81673239},
{"learn":[0.224225233],"iteration":423,"passed_time":14.55697676,"remaining_time":19.7755156},
{"learn":[0.2242086708],"iteration":424,"passed_time":14.58797103,"remaining_time":19.73666669},
{"learn":[0.224187119],"iteration":425,"passed_time":14.61660846,"remaining_time":19.694679},
{"learn":[0.2241710344],"iteration":426,"passed_time":14.64327052,"remaining_time":19.65010307},
{"learn":[0.2241550815],"iteration":427,"passed_time":14.67440365,"remaining_time":19.61158618},
{"learn":[0.224127679],"iteration":428,"passed_time":14.70354505,"remaining_time":19.57045273},
{"learn":[0.2240928095],"iteration":429,"passed_time":14.730702,"remaining_time":19.52674451},
{"learn":[0.2240717702],"iteration":430,"passed_time":14.76509973,"remaining_time":19.49267227},
{"learn":[0.2240538651],"iteration":431,"passed_time":14.79281214,"remaining_time":19.44980855},
{"learn":[0.2240350019],"iteration":432,"passed_time":14.82060376,"remaining_time":19.40711854},
{"learn":[0.224016586],"iteration":433,"passed_time":14.84956767,"remaining_time":19.36602604},
{"learn":[0.2239918679],"iteration":434,"passed_time":14.88777378,"remaining_time":19.33699353},
{"learn":[0.223969851],"iteration":435,"passed_time":14.93017376,"remaining_time":19.31334403},
{"learn":[0.223950464],"iteration":436,"passed_time":14.97435562,"remaining_time":19.29190438},
{"learn":[0.2239299743],"iteration":437,"passed_time":15.0000276,"remaining_time":19.24661075},
{"learn":[0.2238992697],"iteration":438,"passed_time":15.03125966,"remaining_time":19.20851178},
{"learn":[0.2238869898],"iteration":439,"passed_time":15.06110587,"remaining_time":19.16868019},
{"learn":[0.2238612345],"iteration":440,"passed_time":15.09199149,"remaining_time":19.13021143},
{"learn":[0.2238457006],"iteration":441,"passed_time":15.12233067,"remaining_time":19.09108714},
{"learn":[0.2238286496],"iteration":442,"passed_time":15.15222486,"remaining_time":19.05144299},
{"learn":[0.2238065871],"iteration":443,"passed_time":15.18191532,"remaining_time":19.01158765},
{"learn":[0.2237824134],"iteration":444,"passed_time":15.21152199,"remaining_time":18.97167349},
{"learn":[0.2237602374],"iteration":445,"passed_time":15.23960412,"remaining_time":18.92991185},
{"learn":[0.2237458235],"iteration":446,"passed_time":15.2664089,"remaining_time":18.88663114},
{"learn":[0.2237263488],"iteration":447,"passed_time":15.3007763,"remaining_time":18.85274223},
{"learn":[0.2236986989],"iteration":448,"passed_time":15.33113916,"remaining_time":18.81393692},
{"learn":[0.22367056],"iteration":449,"passed_time":15.36313333,"remaining_time":18.77716296},
{"learn":[0.2236419498],"iteration":450,"passed_time":15.40696193,"remaining_time":18.75481618},
{"learn":[0.2236195581],"iteration":451,"passed_time":15.43228838,"remaining_time":18.70994256},
{"learn":[0.2236043216],"iteration":452,"passed_time":15.45875662,"remaining_time":18.66653393},
{"learn":[0.2235844991],"iteration":453,"passed_time":15.49560522,"remaining_time":18.63568382},
{"learn":[0.2235667776],"iteration":454,"passed_time":15.53854894,"remaining_time":18.61210807},
{"learn":[0.2235446964],"iteration":455,"passed_time":15.5667046,"remaining_time":18.57080549},
{"learn":[0.2235179103],"iteration":456,"passed_time":15.59876518,"remaining_time":18.5342002},
{"learn":[0.2234944421],"iteration":457,"passed_time":15.62684288,"remaining_time":18.4929014},
{"learn":[0.2234690189],"iteration":458,"passed_time":15.65931482,"remaining_time":18.45683947},
{"learn":[0.2234532069],"iteration":459,"passed_time":15.68565521,"remaining_time":18.41359524},
{"learn":[0.2234315931],"iteration":460,"passed_time":15.7130944,"remaining_time":18.37170908},
{"learn":[0.2234156489],"iteration":461,"passed_time":15.74611675,"remaining_time":18.33638703},
{"learn":[0.2233953008],"iteration":462,"passed_time":15.77276883,"remaining_time":18.29368652},
{"learn":[0.2233672014],"iteration":463,"passed_time":15.80977857,"remaining_time":18.26302007},
{"learn":[0.2233472099],"iteration":464,"passed_time":15.83766257,"remaining_time":18.22182683},
{"learn":[0.2233343337],"iteration":465,"passed_time":15.86642164,"remaining_time":18.18169347},
{"learn":[0.2233087817],"iteration":466,"passed_time":15.8935066,"remaining_time":18.13969811},
{"learn":[0.2232910183],"iteration":467,"passed_time":15.92578116,"remaining_time":18.10366576},
{"learn":[0.2232726042],"iteration":468,"passed_time":15.97210984,"remaining_time":18.08356146},
{"learn":[0.2232583688],"iteration":469,"passed_time":16.01537796,"remaining_time":18.0598943},
{"learn":[0.2232379223],"iteration":470,"passed_time":16.04506722,"remaining_time":18.02089291},
{"learn":[0.2232282122],"iteration":471,"passed_time":16.0756579,"remaining_time":17.98293935},
{"learn":[0.223210973],"iteration":472,"passed_time":16.10242324,"remaining_time":17.94075485},
{"learn":[0.2231898565],"iteration":473,"passed_time":16.13534779,"remaining_time":17.90547033},
{"learn":[0.223168799],"iteration":474,"passed_time":16.16312003,"remaining_time":17.86450108},
{"learn":[0.2231442968],"iteration":475,"passed_time":16.1915774,"remaining_time":17.8243415},
{"learn":[0.2231234184],"iteration":476,"passed_time":16.22380499,"remaining_time":17.7883648},
{"learn":[0.2231063007],"iteration":477,"passed_time":16.25381271,"remaining_time":17.74997957},
{"learn":[0.2230860133],"iteration":478,"passed_time":16.28350262,"remaining_time":17.71128364},
{"learn":[0.223072667],"iteration":479,"passed_time":16.31365414,"remaining_time":17.67312532},
{"learn":[0.2230473411],"iteration":480,"passed_time":16.34786253,"remaining_time":17.63937765},
{"learn":[0.2230256861],"iteration":481,"passed_time":16.39058887,"remaining_time":17.61478223},
{"learn":[0.2230056225],"iteration":482,"passed_time":16.4340291,"remaining_time":17.59087587},
{"learn":[0.2229847353],"iteration":483,"passed_time":16.49439051,"remaining_time":17.58492872},
{"learn":[0.2229728944],"iteration":484,"passed_time":16.53750761,"remaining_time":17.56044623},
{"learn":[0.2229492334],"iteration":485,"passed_time":16.56789784,"remaining_time":17.52242694},
{"learn":[0.2229377048],"iteration":486,"passed_time":16.59565255,"remaining_time":17.48166275},
{"learn":[0.2229181202],"iteration":487,"passed_time":16.62716674,"remaining_time":17.44489625},
{"learn":[0.2229032053],"iteration":488,"passed_time":16.65502866,"remaining_time":17.40433465},
{"learn":[0.2228812339],"iteration":489,"passed_time":16.68677373,"remaining_time":17.36786654},
{"learn":[0.2228655657],"iteration":490,"passed_time":16.74605194,"remaining_time":17.35996016},
{"learn":[0.2228545291],"iteration":491,"passed_time":16.78905373,"remaining_time":17.33503921},
{"learn":[0.222840007],"iteration":492,"passed_time":16.82096748,"remaining_time":17.29864201},
{"learn":[0.2228209196],"iteration":493,"passed_time":16.85180645,"remaining_time":17.26116207},
{"learn":[0.2227987753],"iteration":494,"passed_time":16.8918301,"remaining_time":17.23307919},
{"learn":[0.2227804707],"iteration":495,"passed_time":16.91921018,"remaining_time":17.19210067},
{"learn":[0.2227705607],"iteration":496,"passed_time":16.94359986,"remaining_time":17.14815036},
{"learn":[0.2227435647],"iteration":497,"passed_time":16.97261478,"remaining_time":17.10894101},
{"learn":[0.2227263465],"iteration":498,"passed_time":17.00117022,"remaining_time":17.06931119},
{"learn":[0.2227092406],"iteration":499,"passed_time":17.02807986,"remaining_time":17.02807986},
{"learn":[0.2226943204],"iteration":500,"passed_time":17.05699903,"remaining_time":16.98890721},
{"learn":[0.222673917],"iteration":501,"passed_time":17.08738161,"remaining_time":16.95122717},
{"learn":[0.2226584837],"iteration":502,"passed_time":17.1167394,"remaining_time":16.91256358},
{"learn":[0.2226390479],"iteration":503,"passed_time":17.15056708,"remaining_time":16.87833585},
{"learn":[0.2226214041],"iteration":504,"passed_time":17.19265282,"remaining_time":16.85220425},
{"learn":[0.222599535],"iteration":505,"passed_time":17.2240237,"remaining_time":16.81554883},
{"learn":[0.2225846166],"iteration":506,"passed_time":17.26455668,"remaining_time":16.78782336},
{"learn":[0.222571886],"iteration":507,"passed_time":17.29305747,"remaining_time":16.74839425},
{"learn":[0.2225603277],"iteration":508,"passed_time":17.31812045,"remaining_time":16.70569183},
{"learn":[0.2225405198],"iteration":509,"passed_time":17.35620966,"remaining_time":16.67557398},
{"learn":[0.2225253559],"iteration":510,"passed_time":17.38749453,"remaining_time":16.63891355},
{"learn":[0.2225164729],"iteration":511,"passed_time":17.43040678,"remaining_time":16.61335647},
{"learn":[0.22249679],"iteration":512,"passed_time":17.46057326,"remaining_time":16.57563193},
{"learn":[0.2224879546],"iteration":513,"passed_time":17.49007035,"remaining_time":16.53730387},
{"learn":[0.2224791336],"iteration":514,"passed_time":17.51904069,"remaining_time":16.49851405},
{"learn":[0.22246227],"iteration":515,"passed_time":17.54856548,"remaining_time":16.46028235},
{"learn":[0.222445872],"iteration":516,"passed_time":17.57573539,"remaining_time":16.41988432},
{"learn":[0.2224348828],"iteration":517,"passed_time":17.60185971,"remaining_time":16.37856444},
{"learn":[0.2224126684],"iteration":518,"passed_time":17.63957985,"remaining_time":16.34804992},
{"learn":[0.2223965846],"iteration":519,"passed_time":17.68372587,"remaining_time":16.32343927},
{"learn":[0.2223673548],"iteration":520,"passed_time":17.72712154,"remaining_time":16.29806376},
{"learn":[0.2223468438],"iteration":521,"passed_time":17.7565694,"remaining_time":16.25984707},
{"learn":[0.2223285666],"iteration":522,"passed_time":17.78373149,"remaining_time":16.2195792},
{"learn":[0.2223062415],"iteration":523,"passed_time":17.81311886,"remaining_time":16.18138278},
{"learn":[0.2222898301],"iteration":524,"passed_time":17.84350277,"remaining_time":16.14412155},
{"learn":[0.2222697323],"iteration":525,"passed_time":17.88942906,"remaining_time":16.12089235},
{"learn":[0.2222572718],"iteration":526,"passed_time":17.92009151,"remaining_time":16.0838772},
{"learn":[0.2222405187],"iteration":527,"passed_time":17.94757654,"remaining_time":16.04404569},
{"learn":[0.2222243007],"iteration":528,"passed_time":17.97769602,"remaining_time":16.00660647},
{"learn":[0.2222103166],"iteration":529,"passed_time":18.00747454,"remaining_time":15.96889252},
{"learn":[0.2221834823],"iteration":530,"passed_time":18.03828252,"remaining_time":15.93211771},
{"learn":[0.2221672486],"iteration":531,"passed_time":18.06701084,"remaining_time":15.89353585},
{"learn":[0.2221518589],"iteration":532,"passed_time":18.09293905,"remaining_time":15.85253759},
{"learn":[0.222130913],"iteration":533,"passed_time":18.1173543,"remaining_time":15.81027547},
{"learn":[0.2221110898],"iteration":534,"passed_time":18.14402399,"remaining_time":15.77003954},
{"learn":[0.222097371],"iteration":535,"passed_time":18.18762466,"remaining_time":15.7445109},
{"learn":[0.2220768152],"iteration":536,"passed_time":18.21309385,"remaining_time":15.70328203},
{"learn":[0.2220572565],"iteration":537,"passed_time":18.24574893,"remaining_time":15.66828254},
{"learn":[0.2220470447],"iteration":538,"passed_time":18.29054039,"remaining_time":15.64367184},
{"learn":[0.2220260825],"iteration":539,"passed_time":18.31594009,"remaining_time":15.60246748},
{"learn":[0.2219951442],"iteration":540,"passed_time":18.34583529,"remaining_time":15.56513567},
{"learn":[0.2219658403],"iteration":541,"passed_time":18.38551779,"remaining_time":15.53610175},
{"learn":[0.2219536945],"iteration":542,"passed_time":18.41539276,"remaining_time":15.49877438},
{"learn":[0.2219344428],"iteration":543,"passed_time":18.44427281,"remaining_time":15.46064044},
{"learn":[0.2219066618],"iteration":544,"passed_time":18.47369206,"remaining_time":15.42299062},
{"learn":[0.2218922661],"iteration":545,"passed_time":18.51458969,"remaining_time":15.39491523},
{"learn":[0.2218699295],"iteration":546,"passed_time":18.54313246,"remaining_time":15.35656125},
{"learn":[0.2218472836],"iteration":547,"passed_time":18.57245987,"remaining_time":15.31889026},
{"learn":[0.2218326238],"iteration":548,"passed_time":18.60669819,"remaining_time":15.28528394},
{"learn":[0.2218136687],"iteration":549,"passed_time":18.63671081,"remaining_time":15.24821793},
{"learn":[0.2217995468],"iteration":550,"passed_time":18.66346155,"remaining_time":15.20851948},
{"learn":[0.2217753403],"iteration":551,"passed_time":18.69339456,"remaining_time":15.17145066},
{"learn":[0.2217575039],"iteration":552,"passed_time":18.72110588,"remaining_time":15.13261181},
{"learn":[0.2217384663],"iteration":553,"passed_time":18.75156819,"remaining_time":15.09602782},
{"learn":[0.2217111896],"iteration":554,"passed_time":18.78325268,"remaining_time":15.06044584},
{"learn":[0.2216925753],"iteration":555,"passed_time":18.81098494,"remaining_time":15.02172179},
{"learn":[0.2216644299],"iteration":556,"passed_time":18.84609535,"remaining_time":14.98890528},
{"learn":[0.2216458855],"iteration":557,"passed_time":18.87496055,"remaining_time":14.95113363},
{"learn":[0.221629758],"iteration":558,"passed_time":18.90296215,"remaining_time":14.91271254},
{"learn":[0.221609856],"iteration":559,"passed_time":18.94673001,"remaining_time":14.88671644},
{"learn":[0.2215842771],"iteration":560,"passed_time":18.97458565,"remaining_time":14.84820517},
{"learn":[0.221576553],"iteration":561,"passed_time":19.00464373,"remaining_time":14.81144832},
{"learn":[0.2215626946],"iteration":562,"passed_time":19.03111844,"remaining_time":14.77193385},
{"learn":[0.2215437262],"iteration":563,"passed_time":19.06471018,"remaining_time":14.73796744},
{"learn":[0.2215327375],"iteration":564,"passed_time":19.09411585,"remaining_time":14.70077946},
{"learn":[0.2215119853],"iteration":565,"passed_time":19.12543691,"remaining_time":14.66508767},
{"learn":[0.2214849286],"iteration":566,"passed_time":19.15300793,"remaining_time":14.6265475},
{"learn":[0.2214707903],"iteration":567,"passed_time":19.18420563,"remaining_time":14.59080429},
{"learn":[0.2214632863],"iteration":568,"passed_time":19.21229472,"remaining_time":14.55272236},
{"learn":[0.2214523574],"iteration":569,"passed_time":19.24527251,"remaining_time":14.51836347},
{"learn":[0.2214348694],"iteration":570,"passed_time":19.27684292,"remaining_time":14.48295203},
{"learn":[0.2214116856],"iteration":571,"passed_time":19.30612295,"remaining_time":14.44584025},
{"learn":[0.2213994244],"iteration":572,"passed_time":19.33741398,"remaining_time":14.4102544},
{"learn":[0.2213869631],"iteration":573,"passed_time":19.36977898,"remaining_time":14.37548057},
{"learn":[0.2213730935],"iteration":574,"passed_time":19.4104995,"remaining_time":14.34689094},
{"learn":[0.221350642],"iteration":575,"passed_time":19.45324902,"remaining_time":14.31975275},
{"learn":[0.2213300507],"iteration":576,"passed_time":19.48107608,"remaining_time":14.28162077},
{"learn":[0.2213192398],"iteration":577,"passed_time":19.51419271,"remaining_time":14.24738637},
{"learn":[0.2213028717],"iteration":578,"passed_time":19.54468595,"remaining_time":14.21124833},
{"learn":[0.2212934694],"iteration":579,"passed_time":19.5727705,"remaining_time":14.17338553},
{"learn":[0.2212806839],"iteration":580,"passed_time":19.60364557,"remaining_time":14.13756884},
{"learn":[0.2212610472],"iteration":581,"passed_time":19.64730438,"remaining_time":14.11095057},
{"learn":[0.2212400429],"iteration":582,"passed_time":19.67719783,"remaining_time":14.07442795},
{"learn":[0.2212195514],"iteration":583,"passed_time":19.70616374,"remaining_time":14.03726732},
{"learn":[0.221197482],"iteration":584,"passed_time":19.73617571,"remaining_time":14.00087679},
{"learn":[0.2211839652],"iteration":585,"passed_time":19.76638314,"remaining_time":13.96464611},
{"learn":[0.221160518],"iteration":586,"passed_time":19.79492278,"remaining_time":13.92726253},
{"learn":[0.2211448705],"iteration":587,"passed_time":19.82382255,"remaining_time":13.89016138},
{"learn":[0.2211204711],"iteration":588,"passed_time":19.85559214,"remaining_time":13.85509061},
{"learn":[0.2211049253],"iteration":589,"passed_time":19.88388391,"remaining_time":13.81761424},
{"learn":[0.2210904992],"iteration":590,"passed_time":19.91466052,"remaining_time":13.78188858},
{"learn":[0.2210804786],"iteration":591,"passed_time":19.94424035,"remaining_time":13.74535484},
{"learn":[0.22106017],"iteration":592,"passed_time":19.97539059,"remaining_time":13.70992238},
{"learn":[0.2210404741],"iteration":593,"passed_time":20.00538719,"remaining_time":13.67371582},
{"learn":[0.2210237824],"iteration":594,"passed_time":20.03617967,"remaining_time":13.63807188},
{"learn":[0.2210030964],"iteration":595,"passed_time":20.07188169,"remaining_time":13.60577215},
{"learn":[0.2209768123],"iteration":596,"passed_time":20.11118836,"remaining_time":13.57589432},
{"learn":[0.2209467636],"iteration":597,"passed_time":20.15380697,"remaining_time":13.54821138},
{"learn":[0.2209360142],"iteration":598,"passed_time":20.19712553,"remaining_time":13.52094714},
{"learn":[0.2209134276],"iteration":599,"passed_time":20.23042383,"remaining_time":13.48694922},
{"learn":[0.2209011345],"iteration":600,"passed_time":20.26833275,"remaining_time":13.45601459},
{"learn":[0.2208716412],"iteration":601,"passed_time":20.29951851,"remaining_time":13.42061191},
{"learn":[0.2208395678],"iteration":602,"passed_time":20.3302152,"remaining_time":13.38490122},
{"learn":[0.2208235013],"iteration":603,"passed_time":20.37348408,"remaining_time":13.35744982},
{"learn":[0.2208082403],"iteration":604,"passed_time":20.41612081,"remaining_time":13.32953342},
{"learn":[0.2207978505],"iteration":605,"passed_time":20.44509964,"remaining_time":13.29268855},
{"learn":[0.2207856632],"iteration":606,"passed_time":20.47378137,"remaining_time":13.25567723},
{"learn":[0.2207652456],"iteration":607,"passed_time":20.50624238,"remaining_time":13.22112995},
{"learn":[0.2207525469],"iteration":608,"passed_time":20.53324078,"remaining_time":13.18308234},
{"learn":[0.2207313031],"iteration":609,"passed_time":20.56527034,"remaining_time":13.14828759},
{"learn":[0.2207137964],"iteration":610,"passed_time":20.59407918,"remaining_time":13.1114514},
{"learn":[0.220696366],"iteration":611,"passed_time":20.62432034,"remaining_time":13.0755495},
{"learn":[0.2206828436],"iteration":612,"passed_time":20.65415681,"remaining_time":13.03941058},
{"learn":[0.2206668843],"iteration":613,"passed_time":20.68306945,"remaining_time":13.00271141},
{"learn":[0.2206494614],"iteration":614,"passed_time":20.71388947,"remaining_time":12.96723162},
{"learn":[0.2206313226],"iteration":615,"passed_time":20.75733572,"remaining_time":12.93963785},
{"learn":[0.2206104658],"iteration":616,"passed_time":20.78717571,"remaining_time":12.90354667},
{"learn":[0.2205954922],"iteration":617,"passed_time":20.82046931,"remaining_time":12.86961048},
{"learn":[0.2205802857],"iteration":618,"passed_time":20.85034028,"remaining_time":12.8335697},
{"learn":[0.2205714165],"iteration":619,"passed_time":20.87959155,"remaining_time":12.79716902},
{"learn":[0.2205549195],"iteration":620,"passed_time":20.90734643,"remaining_time":12.75987809},
{"learn":[0.2205394302],"iteration":621,"passed_time":20.93426502,"remaining_time":12.72210961},
{"learn":[0.2205202168],"iteration":622,"passed_time":20.96152313,"remaining_time":12.68458141},
{"learn":[0.220504436],"iteration":623,"passed_time":20.98779068,"remaining_time":12.64648926},
{"learn":[0.2204825606],"iteration":624,"passed_time":21.02408157,"remaining_time":12.61444894},
{"learn":[0.2204636093],"iteration":625,"passed_time":21.05245059,"remaining_time":12.57766217},
{"learn":[0.2204513199],"iteration":626,"passed_time":21.08130269,"remaining_time":12.54118964},
{"learn":[0.2204384278],"iteration":627,"passed_time":21.10814266,"remaining_time":12.50354948},
{"learn":[0.2204227822],"iteration":628,"passed_time":21.1423656,"remaining_time":12.47029831},
{"learn":[0.2204091672],"iteration":629,"passed_time":21.17414909,"remaining_time":12.43561137},
{"learn":[0.2203917613],"iteration":630,"passed_time":21.20445643,"remaining_time":12.4000704},
{"learn":[0.2203734874],"iteration":631,"passed_time":21.24712277,"remaining_time":12.37174237},
{"learn":[0.2203578502],"iteration":632,"passed_time":21.2788966,"remaining_time":12.3370538},
{"learn":[0.2203399721],"iteration":633,"passed_time":21.32714424,"remaining_time":12.31188453},
{"learn":[0.2203169067],"iteration":634,"passed_time":21.36031034,"remaining_time":12.27797366},
{"learn":[0.2202979746],"iteration":635,"passed_time":21.38819036,"remaining_time":12.24103977},
{"learn":[0.2202863122],"iteration":636,"passed_time":21.41425324,"remaining_time":12.20309878},
{"learn":[0.2202791715],"iteration":637,"passed_time":21.45420286,"remaining_time":12.17307435},
{"learn":[0.2202629947],"iteration":638,"passed_time":21.48208558,"remaining_time":12.13620171},
{"learn":[0.2202500239],"iteration":639,"passed_time":21.51890633,"remaining_time":12.10438481},
{"learn":[0.2202301333],"iteration":640,"passed_time":21.54783284,"remaining_time":12.06813103},
{"learn":[0.2202100569],"iteration":641,"passed_time":21.57761614,"remaining_time":12.03237785},
{"learn":[0.2202002768],"iteration":642,"passed_time":21.61934911,"remaining_time":12.00327781},
{"learn":[0.2201778044],"iteration":643,"passed_time":21.64664907,"remaining_time":11.96616004},
{"learn":[0.2201608521],"iteration":644,"passed_time":21.67707176,"remaining_time":11.93079144},
{"learn":[0.2201533999],"iteration":645,"passed_time":21.70606559,"remaining_time":11.89465514},
{"learn":[0.2201403453],"iteration":646,"passed_time":21.73986394,"remaining_time":11.86116224},
{"learn":[0.2201148721],"iteration":647,"passed_time":21.78302834,"remaining_time":11.83275614},
{"learn":[0.220094254],"iteration":648,"passed_time":21.81151996,"remaining_time":11.79636904},
{"learn":[0.2200778286],"iteration":649,"passed_time":21.83856337,"remaining_time":11.75922643},
{"learn":[0.220053131],"iteration":650,"passed_time":21.87202621,"remaining_time":11.72555629},
{"learn":[0.2200357535],"iteration":651,"passed_time":21.90200798,"remaining_time":11.6900288},
{"learn":[0.2200271932],"iteration":652,"passed_time":21.92817522,"remaining_time":11.65249127},
{"learn":[0.2200129753],"iteration":653,"passed_time":21.96140811,"remaining_time":11.61872661},
{"learn":[0.2199912749],"iteration":654,"passed_time":21.99140574,"remaining_time":11.58325951},
{"learn":[0.219979302],"iteration":655,"passed_time":22.02037843,"remaining_time":11.54727162},
{"learn":[0.2199624948],"iteration":656,"passed_time":22.04918964,"remaining_time":11.51122077},
{"learn":[0.2199467917],"iteration":657,"passed_time":22.0799493,"remaining_time":11.47620465},
{"learn":[0.2199324813],"iteration":658,"passed_time":22.10721434,"remaining_time":11.43939316},
{"learn":[0.2199134182],"iteration":659,"passed_time":22.1426687,"remaining_time":11.40682933},
{"learn":[0.2198949028],"iteration":660,"passed_time":22.18606641,"remaining_time":11.37833058},
{"learn":[0.2198843697],"iteration":661,"passed_time":22.2133667,"remaining_time":11.34156789},
{"learn":[0.2198623819],"iteration":662,"passed_time":22.23957866,"remaining_time":11.30428056},
{"learn":[0.2198465348],"iteration":663,"passed_time":22.2667219,"remaining_time":11.26749783},
{"learn":[0.2198236927],"iteration":664,"passed_time":22.30447667,"remaining_time":11.23608975},
{"learn":[0.2198169153],"iteration":665,"passed_time":22.33533678,"remaining_time":11.20120493},
{"learn":[0.2197948795],"iteration":666,"passed_time":22.36375656,"remaining_time":11.16511384},
{"learn":[0.2197800571],"iteration":667,"passed_time":22.39225821,"remaining_time":11.12908642},
{"learn":[0.2197602086],"iteration":668,"passed_time":22.42390227,"remaining_time":11.09463625},
{"learn":[0.2197410187],"iteration":669,"passed_time":22.45082289,"remaining_time":11.05786799},
{"learn":[0.2197275783],"iteration":670,"passed_time":22.48128117,"remaining_time":11.02286364},
{"learn":[0.2197096233],"iteration":671,"passed_time":22.51117588,"remaining_time":10.98759775},
{"learn":[0.2196976157],"iteration":672,"passed_time":22.54104647,"remaining_time":10.9523361},
{"learn":[0.219674551],"iteration":673,"passed_time":22.57292226,"remaining_time":10.91806032},
{"learn":[0.2196571118],"iteration":674,"passed_time":22.6178626,"remaining_time":10.89008199},
{"learn":[0.219629618],"iteration":675,"passed_time":22.64625795,"remaining_time":10.85412363},
{"learn":[0.219612796],"iteration":676,"passed_time":22.67188046,"remaining_time":10.81686468},
{"learn":[0.2195873521],"iteration":677,"passed_time":22.69877032,"remaining_time":10.78024195},
{"learn":[0.2195650681],"iteration":678,"passed_time":22.72598275,"remaining_time":10.74380039},
{"learn":[0.2195479054],"iteration":679,"passed_time":22.76399158,"remaining_time":10.71246663},
{"learn":[0.2195322023],"iteration":680,"passed_time":22.79240868,"remaining_time":10.67662022},
{"learn":[0.2195225525],"iteration":681,"passed_time":22.82499872,"remaining_time":10.64274134},
{"learn":[0.2195000703],"iteration":682,"passed_time":22.85382906,"remaining_time":10.60712125},
{"learn":[0.2194881834],"iteration":683,"passed_time":22.88441062,"remaining_time":10.57233005},
{"learn":[0.2194669624],"iteration":684,"passed_time":22.91398531,"remaining_time":10.53708814},
{"learn":[0.219447588],"iteration":685,"passed_time":22.94290616,"remaining_time":10.50156346},
{"learn":[0.2194290892],"iteration":686,"passed_time":22.9742014,"remaining_time":10.46713979},
{"learn":[0.2194189695],"iteration":687,"passed_time":22.99984701,"remaining_time":10.43016318},
{"learn":[0.2194017772],"iteration":688,"passed_time":23.03180178,"remaining_time":10.39606728},
{"learn":[0.2193866472],"iteration":689,"passed_time":23.05922244,"remaining_time":10.35994052},
{"learn":[0.2193701513],"iteration":690,"passed_time":23.09459402,"remaining_time":10.32739443},
{"learn":[0.2193578964],"iteration":691,"passed_time":23.12232261,"remaining_time":10.29143839},
{"learn":[0.2193443582],"iteration":692,"passed_time":23.15153157,"remaining_time":10.25616189},
{"learn":[0.2193327935],"iteration":693,"passed_time":23.18179199,"remaining_time":10.2213665},
{"learn":[0.2193215626],"iteration":694,"passed_time":23.20767767,"remaining_time":10.1846643},
{"learn":[0.2193078434],"iteration":695,"passed_time":23.23486173,"remaining_time":10.1485603},
{"learn":[0.2192942464],"iteration":696,"passed_time":23.26223078,"remaining_time":10.11256231},
{"learn":[0.2192819816],"iteration":697,"passed_time":23.30651158,"remaining_time":10.08390616},
{"learn":[0.2192757713],"iteration":698,"passed_time":23.34950025,"remaining_time":10.05464889},
{"learn":[0.2192565629],"iteration":699,"passed_time":23.38909294,"remaining_time":10.02389698},
{"learn":[0.219242683],"iteration":700,"passed_time":23.41536404,"remaining_time":9.987437729},
{"learn":[0.2192300047],"iteration":701,"passed_time":23.44903569,"remaining_time":9.954149053},
{"learn":[0.2192224692],"iteration":702,"passed_time":23.47643941,"remaining_time":9.918211244},
{"learn":[0.219211407],"iteration":703,"passed_time":23.51054801,"remaining_time":9.885116777},
{"learn":[0.2191896388],"iteration":704,"passed_time":23.55507624,"remaining_time":9.856379421},
{"learn":[0.219165032],"iteration":705,"passed_time":23.59472225,"remaining_time":9.825564222},
{"learn":[0.2191499181],"iteration":706,"passed_time":23.62353157,"remaining_time":9.790233028},
{"learn":[0.2191409192],"iteration":707,"passed_time":23.65354639,"remaining_time":9.755417436},
{"learn":[0.2191226175],"iteration":708,"passed_time":23.6877748,"remaining_time":9.722344804},
{"learn":[0.219117034],"iteration":709,"passed_time":23.71781902,"remaining_time":9.687559882},
{"learn":[0.2190952358],"iteration":710,"passed_time":23.74707326,"remaining_time":9.652467191},
{"learn":[0.2190798506],"iteration":711,"passed_time":23.77903707,"remaining_time":9.618486905},
{"learn":[0.2190536455],"iteration":712,"passed_time":23.82133429,"remaining_time":9.588671728},
{"learn":[0.2190374623],"iteration":713,"passed_time":23.85021848,"remaining_time":9.55344886},
{"learn":[0.2190177557],"iteration":714,"passed_time":23.87801775,"remaining_time":9.51781127},
{"learn":[0.2190050879],"iteration":715,"passed_time":23.91201138,"remaining_time":9.484652558},
{"learn":[0.2189918907],"iteration":716,"passed_time":23.94061523,"remaining_time":9.449364171},
{"learn":[0.2189777739],"iteration":717,"passed_time":23.96828268,"remaining_time":9.413726623},
{"learn":[0.218960925],"iteration":718,"passed_time":23.99588994,"remaining_time":9.378087725},
{"learn":[0.2189364661],"iteration":719,"passed_time":24.03129641,"remaining_time":9.34550416},
{"learn":[0.2189202742],"iteration":720,"passed_time":24.06311183,"remaining_time":9.311523161},
{"learn":[0.2189056527],"iteration":721,"passed_time":24.09107392,"remaining_time":9.276064475},
{"learn":[0.2188893421],"iteration":722,"passed_time":24.13501893,"remaining_time":9.246749993},
{"learn":[0.2188783423],"iteration":723,"passed_time":24.16507473,"remaining_time":9.21210031},
{"learn":[0.2188651796],"iteration":724,"passed_time":24.19380378,"remaining_time":9.176960055},
{"learn":[0.2188458821],"iteration":725,"passed_time":24.22134498,"remaining_time":9.14138915},
{"learn":[0.2188331122],"iteration":726,"passed_time":24.24853705,"remaining_time":9.105709237},
{"learn":[0.2188206454],"iteration":727,"passed_time":24.27508647,"remaining_time":9.069812529},
{"learn":[0.2188041466],"iteration":728,"passed_time":24.31548178,"remaining_time":9.039088562},
{"learn":[0.2187921786],"iteration":729,"passed_time":24.35778382,"remaining_time":9.00904333},
{"learn":[0.2187760025],"iteration":730,"passed_time":24.40037165,"remaining_time":8.97906973},
{"learn":[0.2187511345],"iteration":731,"passed_time":24.42617473,"remaining_time":8.942916432},
{"learn":[0.218738583],"iteration":732,"passed_time":24.45149486,"remaining_time":8.906615455},
{"learn":[0.2187238661],"iteration":733,"passed_time":24.50464641,"remaining_time":8.880430444},
{"learn":[0.2187145494],"iteration":734,"passed_time":24.53421496,"remaining_time":8.845669338},
{"learn":[0.2186943561],"iteration":735,"passed_time":24.56296177,"remaining_time":8.810627591},
{"learn":[0.2186794401],"iteration":736,"passed_time":24.59631005,"remaining_time":8.777244971},
{"learn":[0.2186730821],"iteration":737,"passed_time":24.65507887,"remaining_time":8.75288708},
{"learn":[0.2186595322],"iteration":738,"passed_time":24.68458335,"remaining_time":8.718100479},
{"learn":[0.2186442248],"iteration":739,"passed_time":24.71742391,"remaining_time":8.684500294},
{"learn":[0.2186341808],"iteration":740,"passed_time":24.74825238,"remaining_time":8.650198873},
{"learn":[0.2186166299],"iteration":741,"passed_time":24.78961611,"remaining_time":8.619570022},
{"learn":[0.2185999418],"iteration":742,"passed_time":24.82179392,"remaining_time":8.585734908},
{"learn":[0.2185856113],"iteration":743,"passed_time":24.86207206,"remaining_time":8.554691462},
{"learn":[0.2185717259],"iteration":744,"passed_time":24.88850808,"remaining_time":8.518885316},
{"learn":[0.218544201],"iteration":745,"passed_time":24.91838953,"remaining_time":8.484277401},
{"learn":[0.2185262087],"iteration":746,"passed_time":24.95216247,"remaining_time":8.451000139},
{"learn":[0.2185162276],"iteration":747,"passed_time":24.97616508,"remaining_time":8.414429947},
{"learn":[0.2185057499],"iteration":748,"passed_time":25.01278222,"remaining_time":8.382120611},
{"learn":[0.2184911787],"iteration":749,"passed_time":25.04062302,"remaining_time":8.346874339},
{"learn":[0.2184715194],"iteration":750,"passed_time":25.08699135,"remaining_time":8.31779074},
{"learn":[0.2184589292],"iteration":751,"passed_time":25.11725536,"remaining_time":8.283350172},
{"learn":[0.2184482052],"iteration":752,"passed_time":25.14345389,"remaining_time":8.247587134},
{"learn":[0.2184282266],"iteration":753,"passed_time":25.16999265,"remaining_time":8.211960466},
{"learn":[0.2184105388],"iteration":754,"passed_time":25.20587697,"remaining_time":8.17939054},
{"learn":[0.2183938539],"iteration":755,"passed_time":25.2374606,"remaining_time":8.145423792},
{"learn":[0.2183784861],"iteration":756,"passed_time":25.26814376,"remaining_time":8.111174285},
{"learn":[0.2183636413],"iteration":757,"passed_time":25.31184622,"remaining_time":8.081090745},
{"learn":[0.2183504556],"iteration":758,"passed_time":25.34194591,"remaining_time":8.046652126},
{"learn":[0.2183327104],"iteration":759,"passed_time":25.38531436,"remaining_time":8.016415062},
{"learn":[0.21831008],"iteration":760,"passed_time":25.42917549,"remaining_time":7.986298217},
{"learn":[0.2182941555],"iteration":761,"passed_time":25.45750719,"remaining_time":7.951294897},
{"learn":[0.2182796879],"iteration":762,"passed_time":25.48936829,"remaining_time":7.917405354},
{"learn":[0.2182673877],"iteration":763,"passed_time":25.53700733,"remaining_time":7.888394935},
{"learn":[0.218246512],"iteration":764,"passed_time":25.57944784,"remaining_time":7.857738879},
{"learn":[0.2182351896],"iteration":765,"passed_time":25.60556502,"remaining_time":7.822065554},
{"learn":[0.2182112392],"iteration":766,"passed_time":25.63780589,"remaining_time":7.788277409},
{"learn":[0.218189949],"iteration":767,"passed_time":25.66433639,"remaining_time":7.752768286},
{"learn":[0.2181660456],"iteration":768,"passed_time":25.71024753,"remaining_time":7.723104266},
{"learn":[0.2181430359],"iteration":769,"passed_time":25.7534147,"remaining_time":7.692578416},
{"learn":[0.2181269987],"iteration":770,"passed_time":25.78351644,"remaining_time":7.658139124},
{"learn":[0.2181125539],"iteration":771,"passed_time":25.81290569,"remaining_time":7.623500643},
{"learn":[0.2180963633],"iteration":772,"passed_time":25.84336292,"remaining_time":7.589189371},
{"learn":[0.2180825288],"iteration":773,"passed_time":25.87009208,"remaining_time":7.553799497},
{"learn":[0.2180699855],"iteration":774,"passed_time":25.89786002,"remaining_time":7.518733555},
{"learn":[0.2180592851],"iteration":775,"passed_time":25.93009364,"remaining_time":7.484975484},
{"learn":[0.2180427878],"iteration":776,"passed_time":25.97436908,"remaining_time":7.454677356},
{"learn":[0.2180293435],"iteration":777,"passed_time":26.0206951,"remaining_time":7.424928423},
{"learn":[0.2180130169],"iteration":778,"passed_time":26.05098394,"remaining_time":7.390587228},
{"learn":[0.2179930074],"iteration":779,"passed_time":26.07815917,"remaining_time":7.355378226},
{"learn":[0.2179737046],"iteration":780,"passed_time":26.10492976,"remaining_time":7.320076334},
{"learn":[0.2179589309],"iteration":781,"passed_time":26.14260238,"remaining_time":7.287835447},
{"learn":[0.2179448153],"iteration":782,"passed_time":26.17096878,"remaining_time":7.253001566},
{"learn":[0.2179366579],"iteration":783,"passed_time":26.21288336,"remaining_time":7.221916843},
{"learn":[0.2179173644],"iteration":784,"passed_time":26.24197626,"remaining_time":7.18729286},
{"learn":[0.217914225],"iteration":785,"passed_time":26.27167492,"remaining_time":7.152847878},
{"learn":[0.2179019499],"iteration":786,"passed_time":26.29736279,"remaining_time":7.117329445},
{"learn":[0.2178846978],"iteration":787,"passed_time":26.3274377,"remaining_time":7.083016234},
{"learn":[0.2178662438],"iteration":788,"passed_time":26.36894582,"remaining_time":7.051771315},
{"learn":[0.2178461184],"iteration":789,"passed_time":26.40842439,"remaining_time":7.019960915},
{"learn":[0.2178232068],"iteration":790,"passed_time":26.45301859,"remaining_time":6.989482788},
{"learn":[0.2178064135],"iteration":791,"passed_time":26.47974161,"remaining_time":6.954275574},
{"learn":[0.2177939069],"iteration":792,"passed_time":26.50954576,"remaining_time":6.919894039},
{"learn":[0.2177858458],"iteration":793,"passed_time":26.53867136,"remaining_time":6.885347985},
{"learn":[0.217768811],"iteration":794,"passed_time":26.57060415,"remaining_time":6.851539435},
{"learn":[0.2177513279],"iteration":795,"passed_time":26.60224686,"remaining_time":6.817661257},
{"learn":[0.2177347692],"iteration":796,"passed_time":26.63152895,"remaining_time":6.783187424},
{"learn":[0.2177186207],"iteration":797,"passed_time":26.66133253,"remaining_time":6.748858611},
{"learn":[0.21770623],"iteration":798,"passed_time":26.70559273,"remaining_time":6.718177895},
{"learn":[0.2176904749],"iteration":799,"passed_time":26.73375184,"remaining_time":6.683437959},
{"learn":[0.2176681658],"iteration":800,"passed_time":26.76186393,"remaining_time":6.648702773},
{"learn":[0.2176488126],"iteration":801,"passed_time":26.79414581,"remaining_time":6.615013555},
{"learn":[0.2176310233],"iteration":802,"passed_time":26.8243066,"remaining_time":6.580807471},
{"learn":[0.217612331],"iteration":803,"passed_time":26.85280305,"remaining_time":6.54620572},
{"learn":[0.2175960239],"iteration":804,"passed_time":26.88037175,"remaining_time":6.511394399},
{"learn":[0.2175783997],"iteration":805,"passed_time":26.90885982,"remaining_time":6.476822338},
{"learn":[0.2175557209],"iteration":806,"passed_time":26.94398855,"remaining_time":6.443853519},
{"learn":[0.2175413144],"iteration":807,"passed_time":26.97159297,"remaining_time":6.409091399},
{"learn":[0.2175251638],"iteration":808,"passed_time":27.00096119,"remaining_time":6.374763395},
{"learn":[0.2175102591],"iteration":809,"passed_time":27.030318,"remaining_time":6.340444963},
{"learn":[0.2174935316],"iteration":810,"passed_time":27.06396003,"remaining_time":6.307137417},
{"learn":[0.2174806694],"iteration":811,"passed_time":27.09538335,"remaining_time":6.273315357},
{"learn":[0.2174677411],"iteration":812,"passed_time":27.13877773,"remaining_time":6.242252689},
{"learn":[0.2174403942],"iteration":813,"passed_time":27.19065392,"remaining_time":6.213097825},
{"learn":[0.2174140877],"iteration":814,"passed_time":27.23417601,"remaining_time":6.181990874},
{"learn":[0.2174018946],"iteration":815,"passed_time":27.27288454,"remaining_time":6.149768082},
{"learn":[0.21738356],"iteration":816,"passed_time":27.3100315,"remaining_time":6.117179638},
{"learn":[0.2173654515],"iteration":817,"passed_time":27.35516068,"remaining_time":6.086356044},
{"learn":[0.2173545736],"iteration":818,"passed_time":27.38950385,"remaining_time":6.053113794},
{"learn":[0.2173353001],"iteration":819,"passed_time":27.42387779,"remaining_time":6.019875613},
{"learn":[0.217323898],"iteration":820,"passed_time":27.4559714,"remaining_time":5.986137491},
{"learn":[0.2173067024],"iteration":821,"passed_time":27.4995328,"remaining_time":5.954886665},
{"learn":[0.2172917134],"iteration":822,"passed_time":27.53077373,"remaining_time":5.920956197},
{"learn":[0.2172787416],"iteration":823,"passed_time":27.56663779,"remaining_time":5.888019722},
{"learn":[0.2172672214],"iteration":824,"passed_time":27.59685531,"remaining_time":5.853878399},
{"learn":[0.2172527323],"iteration":825,"passed_time":27.62594329,"remaining_time":5.819508635},
{"learn":[0.217230449],"iteration":826,"passed_time":27.66016477,"remaining_time":5.78622552},
{"learn":[0.2172056656],"iteration":827,"passed_time":27.69169965,"remaining_time":5.752382054},
{"learn":[0.2171895705],"iteration":828,"passed_time":27.72231342,"remaining_time":5.718354155},
{"learn":[0.2171746962],"iteration":829,"passed_time":27.76410981,"remaining_time":5.686624901},
{"learn":[0.2171573844],"iteration":830,"passed_time":27.7976384,"remaining_time":5.653189999},
{"learn":[0.2171450395],"iteration":831,"passed_time":27.83951725,"remaining_time":5.621440983},
{"learn":[0.2171278079],"iteration":832,"passed_time":27.87157195,"remaining_time":5.587698098},
{"learn":[0.2171074788],"iteration":833,"passed_time":27.91214392,"remaining_time":5.555654546},
{"learn":[0.2170919374],"iteration":834,"passed_time":27.94497109,"remaining_time":5.522060156},
{"learn":[0.2170757125],"iteration":835,"passed_time":27.97780104,"remaining_time":5.488468147},
{"learn":[0.2170590553],"iteration":836,"passed_time":28.01489605,"remaining_time":5.45570855},
{"learn":[0.2170466603],"iteration":837,"passed_time":28.04229669,"remaining_time":5.421064515},
{"learn":[0.2170281022],"iteration":838,"passed_time":28.06832925,"remaining_time":5.386175221},
{"learn":[0.2170097763],"iteration":839,"passed_time":28.1057087,"remaining_time":5.353468323},
{"learn":[0.2169973156],"iteration":840,"passed_time":28.15005077,"remaining_time":5.322066673},
{"learn":[0.2169832449],"iteration":841,"passed_time":28.17824205,"remaining_time":5.287603615},
{"learn":[0.2169666884],"iteration":842,"passed_time":28.20834545,"remaining_time":5.253511549},
{"learn":[0.2169515466],"iteration":843,"passed_time":28.23843956,"remaining_time":5.219427217},
{"learn":[0.2169344905],"iteration":844,"passed_time":28.2824428,"remaining_time":5.187903709},
{"learn":[0.2169252131],"iteration":845,"passed_time":28.31313423,"remaining_time":5.153927507},
{"learn":[0.2169096459],"iteration":846,"passed_time":28.34301677,"remaining_time":5.119812947},
{"learn":[0.2168986606],"iteration":847,"passed_time":28.38873786,"remaining_time":5.088547353},
{"learn":[0.2168797737],"iteration":848,"passed_time":28.41648297,"remaining_time":5.054050564},
{"learn":[0.2168659483],"iteration":849,"passed_time":28.44344615,"remaining_time":5.019431673},
{"learn":[0.2168480801],"iteration":850,"passed_time":28.47401741,"remaining_time":4.985462508},
{"learn":[0.2168253201],"iteration":851,"passed_time":28.50710366,"remaining_time":4.951938195},
{"learn":[0.2168106581],"iteration":852,"passed_time":28.53578045,"remaining_time":4.917655013},
{"learn":[0.2167949812],"iteration":853,"passed_time":28.57804409,"remaining_time":4.885707772},
{"learn":[0.2167847886],"iteration":854,"passed_time":28.60533994,"remaining_time":4.851198001},
{"learn":[0.2167735402],"iteration":855,"passed_time":28.6364726,"remaining_time":4.817350531},
{"learn":[0.2167551834],"iteration":856,"passed_time":28.67025815,"remaining_time":4.783952059},
{"learn":[0.2167342931],"iteration":857,"passed_time":28.71430715,"remaining_time":4.7522513},
{"learn":[0.216715734],"iteration":858,"passed_time":28.7420822,"remaining_time":4.717850513},
{"learn":[0.2167001982],"iteration":859,"passed_time":28.77398747,"remaining_time":4.684137495},
{"learn":[0.2166890725],"iteration":860,"passed_time":28.80231088,"remaining_time":4.64985042},
{"learn":[0.2166766856],"iteration":861,"passed_time":28.83176919,"remaining_time":4.615758873},
{"learn":[0.2166581814],"iteration":862,"passed_time":28.86142059,"remaining_time":4.581708715},
{"learn":[0.2166443724],"iteration":863,"passed_time":28.89138808,"remaining_time":4.547718494},
{"learn":[0.2166309312],"iteration":864,"passed_time":28.92207676,"remaining_time":4.51385013},
{"learn":[0.2166159355],"iteration":865,"passed_time":28.95035797,"remaining_time":4.479616591},
{"learn":[0.2165981721],"iteration":866,"passed_time":28.98103667,"remaining_time":4.445764565},
{"learn":[0.2165873186],"iteration":867,"passed_time":29.01274073,"remaining_time":4.41207578},
{"learn":[0.2165717797],"iteration":868,"passed_time":29.06005905,"remaining_time":4.38074538},
{"learn":[0.2165546959],"iteration":869,"passed_time":29.09880589,"remaining_time":4.348097433},
{"learn":[0.2165361511],"iteration":870,"passed_time":29.13028402,"remaining_time":4.314358942},
{"learn":[0.2165227058],"iteration":871,"passed_time":29.15936449,"remaining_time":4.280273686},
{"learn":[0.2165051948],"iteration":872,"passed_time":29.18963667,"remaining_time":4.246373261},
{"learn":[0.2164932258],"iteration":873,"passed_time":29.21854582,"remaining_time":4.212284637},
{"learn":[0.2164860685],"iteration":874,"passed_time":29.24836425,"remaining_time":4.178337749},
{"learn":[0.2164781419],"iteration":875,"passed_time":29.28043231,"remaining_time":4.144718729},
{"learn":[0.2164619951],"iteration":876,"passed_time":29.32618265,"remaining_time":4.113022196},
{"learn":[0.21644959],"iteration":877,"passed_time":29.35707633,"remaining_time":4.079229285},
{"learn":[0.2164363811],"iteration":878,"passed_time":29.39840607,"remaining_time":4.046879562},
{"learn":[0.2164212454],"iteration":879,"passed_time":29.43050512,"remaining_time":4.013250699},
{"learn":[0.2164112694],"iteration":880,"passed_time":29.46043586,"remaining_time":3.979332426},
{"learn":[0.2164009578],"iteration":881,"passed_time":29.50467417,"remaining_time":3.947337361},
{"learn":[0.2163848276],"iteration":882,"passed_time":29.54734101,"remaining_time":3.91510634},
{"learn":[0.2163736012],"iteration":883,"passed_time":29.57583371,"remaining_time":3.880991754},
{"learn":[0.216354102],"iteration":884,"passed_time":29.6069518,"remaining_time":3.847231024},
{"learn":[0.2163432193],"iteration":885,"passed_time":29.63347571,"remaining_time":3.812885136},
{"learn":[0.2163321434],"iteration":886,"passed_time":29.66621778,"remaining_time":3.779349052},
{"learn":[0.2163159536],"iteration":887,"passed_time":29.69496335,"remaining_time":3.745310692},
{"learn":[0.2162998598],"iteration":888,"passed_time":29.72385493,"remaining_time":3.711302472},
{"learn":[0.2162826665],"iteration":889,"passed_time":29.75296354,"remaining_time":3.677332573},
{"learn":[0.2162699832],"iteration":890,"passed_time":29.78563758,"remaining_time":3.64380976},
{"learn":[0.2162518167],"iteration":891,"passed_time":29.81334537,"remaining_time":3.609687556},
{"learn":[0.2162380933],"iteration":892,"passed_time":29.84408153,"remaining_time":3.575942579},
{"learn":[0.2162200101],"iteration":893,"passed_time":29.87608929,"remaining_time":3.542355106},
{"learn":[0.2162034351],"iteration":894,"passed_time":29.90323065,"remaining_time":3.508200244},
{"learn":[0.2161812847],"iteration":895,"passed_time":29.93345781,"remaining_time":3.47441921},
{"learn":[0.2161650715],"iteration":896,"passed_time":29.96098789,"remaining_time":3.440336402},
{"learn":[0.2161481213],"iteration":897,"passed_time":29.99461377,"remaining_time":3.406960584},
{"learn":[0.2161354307],"iteration":898,"passed_time":30.03808858,"remaining_time":3.374690708},
{"learn":[0.2161215146],"iteration":899,"passed_time":30.06671419,"remaining_time":3.340746021},
{"learn":[0.216107064],"iteration":900,"passed_time":30.09618552,"remaining_time":3.306906067},
{"learn":[0.216097027],"iteration":901,"passed_time":30.12469728,"remaining_time":3.272971545},
{"learn":[0.2160763623],"iteration":902,"passed_time":30.15832886,"remaining_time":3.239599003},
{"learn":[0.2160600482],"iteration":903,"passed_time":30.20349943,"remaining_time":3.207451267},
{"learn":[0.2160510145],"iteration":904,"passed_time":30.24657826,"remaining_time":3.175055177},
{"learn":[0.2160352419],"iteration":905,"passed_time":30.27599809,"remaining_time":3.141218345},
{"learn":[0.2160211529],"iteration":906,"passed_time":30.30759699,"remaining_time":3.107614685},
{"learn":[0.216009675],"iteration":907,"passed_time":30.35045569,"remaining_time":3.075156303},
{"learn":[0.2159968935],"iteration":908,"passed_time":30.38007422,"remaining_time":3.041349564},
{"learn":[0.2159811741],"iteration":909,"passed_time":30.40913258,"remaining_time":3.007496629},
{"learn":[0.2159685159],"iteration":910,"passed_time":30.43504556,"remaining_time":2.973346931},
{"learn":[0.2159488035],"iteration":911,"passed_time":30.47055023,"remaining_time":2.940140811},
{"learn":[0.2159308979],"iteration":912,"passed_time":30.49917734,"remaining_time":2.906274292},
{"learn":[0.2158997835],"iteration":913,"passed_time":30.52832637,"remaining_time":2.872468345},
{"learn":[0.2158745199],"iteration":914,"passed_time":30.55669057,"remaining_time":2.838599671},
{"learn":[0.215867058],"iteration":915,"passed_time":30.58872685,"remaining_time":2.805079755},
{"learn":[0.215847313],"iteration":916,"passed_time":30.62045923,"remaining_time":2.771535568},
{"learn":[0.2158358556],"iteration":917,"passed_time":30.66456364,"remaining_time":2.739100456},
{"learn":[0.215823129],"iteration":918,"passed_time":30.69031371,"remaining_time":2.705022209},
{"learn":[0.2158060726],"iteration":919,"passed_time":30.72043021,"remaining_time":2.671341757},
{"learn":[0.2157861767],"iteration":920,"passed_time":30.75056305,"remaining_time":2.637670446},
{"learn":[0.2157667378],"iteration":921,"passed_time":30.78418843,"remaining_time":2.604302275},
{"learn":[0.2157478431],"iteration":922,"passed_time":30.81589931,"remaining_time":2.570773832},
{"learn":[0.2157354005],"iteration":923,"passed_time":30.86479878,"remaining_time":2.538663103},
{"learn":[0.2157187395],"iteration":924,"passed_time":30.8985468,"remaining_time":2.505287579},
{"learn":[0.2157034316],"iteration":925,"passed_time":30.93092467,"remaining_time":2.471801755},
{"learn":[0.2156851028],"iteration":926,"passed_time":30.96824316,"remaining_time":2.43870739},
{"learn":[0.2156739033],"iteration":927,"passed_time":31.01095727,"remaining_time":2.406022547},
{"learn":[0.2156560296],"iteration":928,"passed_time":31.0531696,"remaining_time":2.373277763},
{"learn":[0.2156409589],"iteration":929,"passed_time":31.08319073,"remaining_time":2.339595001},
{"learn":[0.2156221974],"iteration":930,"passed_time":31.1182727,"remaining_time":2.306295184},
{"learn":[0.2156050937],"iteration":931,"passed_time":31.15148546,"remaining_time":2.272855162},
{"learn":[0.2155967282],"iteration":932,"passed_time":31.18463843,"remaining_time":2.239411334},
{"learn":[0.2155829385],"iteration":933,"passed_time":31.21651614,"remaining_time":2.205878014},
{"learn":[0.2155707212],"iteration":934,"passed_time":31.24914007,"remaining_time":2.172400112},
{"learn":[0.215554256],"iteration":935,"passed_time":31.28601831,"remaining_time":2.139214927},
{"learn":[0.2155350055],"iteration":936,"passed_time":31.32346814,"remaining_time":2.106060291},
{"learn":[0.2155221177],"iteration":937,"passed_time":31.35381131,"remaining_time":2.07242676},
{"learn":[0.2155064051],"iteration":938,"passed_time":31.38687486,"remaining_time":2.038976961},
{"learn":[0.2154916426],"iteration":939,"passed_time":31.42565606,"remaining_time":2.00589294},
{"learn":[0.2154686699],"iteration":940,"passed_time":31.45681889,"remaining_time":1.972319144},
{"learn":[0.2154578467],"iteration":941,"passed_time":31.48598216,"remaining_time":1.938627352},
{"learn":[0.2154381212],"iteration":942,"passed_time":31.52825717,"remaining_time":1.905737708},
{"learn":[0.2154286054],"iteration":943,"passed_time":31.55853984,"remaining_time":1.87211677},
{"learn":[0.2154192861],"iteration":944,"passed_time":31.60296351,"remaining_time":1.839325918},
{"learn":[0.2154078849],"iteration":945,"passed_time":31.64900685,"remaining_time":1.806602928},
{"learn":[0.2153944173],"iteration":946,"passed_time":31.67964055,"remaining_time":1.772989387},
{"learn":[0.2153775148],"iteration":947,"passed_time":31.70960636,"remaining_time":1.739345496},
{"learn":[0.2153624656],"iteration":948,"passed_time":31.75188248,"remaining_time":1.706370924},
{"learn":[0.2153532475],"iteration":949,"passed_time":31.79380779,"remaining_time":1.673358305},
{"learn":[0.2153389235],"iteration":950,"passed_time":31.82297395,"remaining_time":1.639669531},
{"learn":[0.2153286191],"iteration":951,"passed_time":31.85414575,"remaining_time":1.606091382},
{"learn":[0.2153142453],"iteration":952,"passed_time":31.88781563,"remaining_time":1.572641485},
{"learn":[0.2152953844],"iteration":953,"passed_time":31.91932109,"remaining_time":1.539086761},
{"learn":[0.2152794546],"iteration":954,"passed_time":31.95850667,"remaining_time":1.50589822},
{"learn":[0.2152638],"iteration":955,"passed_time":31.99095943,"remaining_time":1.472387254},
{"learn":[0.2152489621],"iteration":956,"passed_time":32.01946312,"remaining_time":1.43870106},
{"learn":[0.2152340885],"iteration":957,"passed_time":32.04961701,"remaining_time":1.405098032},
{"learn":[0.2152229054],"iteration":958,"passed_time":32.09304014,"remaining_time":1.372069495},
{"learn":[0.2152067973],"iteration":959,"passed_time":32.12629233,"remaining_time":1.338595514},
{"learn":[0.2151965078],"iteration":960,"passed_time":32.22000422,"remaining_time":1.307575614},
{"learn":[0.2151861555],"iteration":961,"passed_time":32.25986874,"remaining_time":1.274298349},
{"learn":[0.2151683135],"iteration":962,"passed_time":32.3131392,"remaining_time":1.241522482},
{"learn":[0.2151538026],"iteration":963,"passed_time":32.34795882,"remaining_time":1.20801506},
{"learn":[0.2151357024],"iteration":964,"passed_time":32.38630905,"remaining_time":1.174632971},
{"learn":[0.2151164775],"iteration":965,"passed_time":32.42575132,"remaining_time":1.141279032},
{"learn":[0.2150986219],"iteration":966,"passed_time":32.46504477,"remaining_time":1.107907422},
{"learn":[0.2150885699],"iteration":967,"passed_time":32.50760735,"remaining_time":1.074631648},
{"learn":[0.2150698394],"iteration":968,"passed_time":32.54817532,"remaining_time":1.041272895},
{"learn":[0.215054287],"iteration":969,"passed_time":32.58975903,"remaining_time":1.007930692},
{"learn":[0.2150392508],"iteration":970,"passed_time":32.63414715,"remaining_time":0.9746552701},
{"learn":[0.2150296419],"iteration":971,"passed_time":32.67106576,"remaining_time":0.9411418119},
{"learn":[0.2150098287],"iteration":972,"passed_time":32.71371637,"remaining_time":0.9077804131},
{"learn":[0.2149927453],"iteration":973,"passed_time":32.75084378,"remaining_time":0.8742525034},
{"learn":[0.2149761204],"iteration":974,"passed_time":32.78647515,"remaining_time":0.84067885},
{"learn":[0.2149614273],"iteration":975,"passed_time":32.82260171,"remaining_time":0.8071131568},
{"learn":[0.2149472685],"iteration":976,"passed_time":32.85767927,"remaining_time":0.7735175262},
{"learn":[0.214926649],"iteration":977,"passed_time":32.89322772,"remaining_time":0.739929458},
{"learn":[0.2149165307],"iteration":978,"passed_time":32.9285613,"remaining_time":0.7063327756},
{"learn":[0.2148976837],"iteration":979,"passed_time":32.97371358,"remaining_time":0.6729329303},
{"learn":[0.2148793322],"iteration":980,"passed_time":33.00423443,"remaining_time":0.6392257433},
{"learn":[0.2148547728],"iteration":981,"passed_time":33.05805829,"remaining_time":0.6059521885},
{"learn":[0.2148415434],"iteration":982,"passed_time":33.08620973,"remaining_time":0.5721928437},
{"learn":[0.2148242441],"iteration":983,"passed_time":33.12102644,"remaining_time":0.5385532754},
{"learn":[0.2148158365],"iteration":984,"passed_time":33.16247316,"remaining_time":0.5050122816},
{"learn":[0.2147962989],"iteration":985,"passed_time":33.19319349,"remaining_time":0.4713029502},
{"learn":[0.2147823416],"iteration":986,"passed_time":33.22620489,"remaining_time":0.4376298517},
{"learn":[0.2147650872],"iteration":987,"passed_time":33.25656474,"remaining_time":0.4039258875},
{"learn":[0.2147493105],"iteration":988,"passed_time":33.30011936,"remaining_time":0.3703754428},
{"learn":[0.2147346373],"iteration":989,"passed_time":33.33066979,"remaining_time":0.3366734322},
{"learn":[0.2147324632],"iteration":990,"passed_time":33.36163245,"remaining_time":0.3029815258},
{"learn":[0.2147161088],"iteration":991,"passed_time":33.38989363,"remaining_time":0.2692733357},
{"learn":[0.2146983004],"iteration":992,"passed_time":33.43278542,"remaining_time":0.2356792527},
{"learn":[0.2146807744],"iteration":993,"passed_time":33.4618411,"remaining_time":0.2019829443},
{"learn":[0.2146618819],"iteration":994,"passed_time":33.49274995,"remaining_time":0.1683052761},
{"learn":[0.2146392436],"iteration":995,"passed_time":33.5208573,"remaining_time":0.1346219168},
{"learn":[0.2146293011],"iteration":996,"passed_time":33.55238173,"remaining_time":0.1009600253},
{"learn":[0.2146135319],"iteration":997,"passed_time":33.58243553,"remaining_time":0.06729947},
{"learn":[0.2145957412],"iteration":998,"passed_time":33.61538925,"remaining_time":0.03364903828},
{"learn":[0.2145763645],"iteration":999,"passed_time":33.64268526,"remaining_time":0}
]}